{"meta":{"version":"121","folder":"EventFlowMsg","file":"Tribune07","chunk":0,"start":0,"count":58,"total":58},"rows":[{"id":38453,"index":0,"key":"Talk1042","CNzh":"<unk[3:0:7]><unk[4:0:16 71 114 101 101 116 105 110 103]>嗨，搭档，\n你也是来打听情报的？\n都这么晚了，还真是有活力啊。\n没想到新人的记者之魂比肩职业人士嘛。","TWzh":"<unk[3:0:7]><unk[4:0:16 71 114 101 101 116 105 110 103]>嗨，搭檔。\n你也在打聽情報嗎？\n忙到這麼晚，你還真是努力呢。\n還想說只是新人，沒想到記者之魂媲美專業人士啊。","JPja":"<unk[3:0:7]><unk[4:0:16 71 114 101 101 116 105 110 103]>よう <Ruby={4:8}あいぼう>相棒\nお<Ruby={2:4}まえ>前も <Ruby={2:2}き>聞きトリか？\nこんな<Ruby={4:6}じかん>時間まで <Ruby={2:4}せい>精がでるじゃないか\n<Ruby={4:8}しんまい>新米だと<Ruby={2:4}おも>思ってたが <Ruby={6:14}きしゃだましい>記者魂はプロ<Ruby={2:2}な>並みだな","USen":"<unk[3:0:7]><unk[4:0:16 71 114 101 101 116 105 110 103]>Hello, partner! You here to investigate\nthe rumors too?\n\nI admire your spirit! Most folks wouldn't\nlet a story keep them up so late, but not\nyou! You're the real deal!"},{"id":38454,"index":1,"key":"Talk1043","CNzh":"<unk[3:0:7]><unk[4:0:16 71 114 101 101 116 105 110 103]>嗨，搭档，\n你也是来打听情报的？\n这大清早的，还真是有活力啊。\n没想到新人的记者之魂比肩职业人士嘛。","TWzh":"<unk[3:0:7]><unk[4:0:16 71 114 101 101 116 105 110 103]>嗨，搭檔。\n你也在打聽情報嗎？\n這麼早就開始行動，你還真是努力呢。\n還想說只是新人，沒想到記者之魂媲美專業人士啊。","JPja":"<unk[3:0:7]><unk[4:0:16 71 114 101 101 116 105 110 103]>よう <Ruby={4:8}あいぼう>相棒\nお<Ruby={2:4}まえ>前も <Ruby={2:2}き>聞きトリか？\nこんな<Ruby={4:6}じかん>時間に <Ruby={2:4}せい>精がでるじゃないか\n<Ruby={4:8}しんまい>新米だと<Ruby={2:4}おも>思ってたが <Ruby={6:14}きしゃだましい>記者魂はプロ<Ruby={2:2}な>並みだな","USen":"<unk[3:0:7]><unk[4:0:16 71 114 101 101 116 105 110 103]>Hello, partner! You here to investigate\nthe rumors too?\n\nI admire your spirit! Most folks would\nleave a story until a bit later in the day,\nbut not you! You're the real deal!"},{"id":38455,"index":2,"key":"Talk1041","CNzh":"<unk[3:0:7]><unk[4:0:16 71 114 101 101 116 105 110 103]>嗨，搭档，\n你也是来打听情报的？\n天气这么糟糕，还真是有活力啊。\n没想到新人的记者之魂比肩职业人士嘛。","TWzh":"<unk[3:0:7]><unk[4:0:16 71 114 101 101 116 105 110 103]>嗨，搭檔。\n你也在打聽情報嗎？\n天氣這麼惡劣，你還真是努力呢。\n還想說只是新人，沒想到記者之魂媲美專業人士啊。","JPja":"<unk[3:0:7]><unk[4:0:16 71 114 101 101 116 105 110 103]>よう <Ruby={4:8}あいぼう>相棒\nお<Ruby={2:4}まえ>前も <Ruby={2:2}き>聞きトリか？\nこんな<Ruby={6:12}あくてんこう>悪天候の<Ruby={2:4}なか>中 <Ruby={2:4}せい>精がでるじゃないか\n<Ruby={4:8}しんまい>新米だと<Ruby={2:4}おも>思ってたが <Ruby={6:14}きしゃだましい>記者魂はプロ<Ruby={2:2}な>並みだな","USen":"<unk[3:0:7]><unk[4:0:16 71 114 101 101 116 105 110 103]>Hello, partner! You here to investigate\nthe rumors too?\n\nI admire your spirit! Most folks would take\none look at this weather and call it a day,\nbut not you! You're the real deal!"},{"id":38456,"index":3,"key":"Talk1040","CNzh":"<unk[3:0:7]><unk[4:0:16 71 114 101 101 116 105 110 103]>嗨，搭档，\n你也是来打听情报的？","TWzh":"<unk[3:0:7]><unk[4:0:16 71 114 101 101 116 105 110 103]>嗨，搭檔。\n你也在打聽情報嗎？","JPja":"<unk[3:0:7]><unk[4:0:16 71 114 101 101 116 105 110 103]>よう <Ruby={4:8}あいぼう>相棒\nお<Ruby={2:4}まえ>前も <Ruby={2:2}き>聞きトリか？","USen":"<unk[3:0:7]><unk[4:0:16 71 114 101 101 116 105 110 103]>Hello, partner! You here to investigate\nthe rumors too?"},{"id":38457,"index":4,"key":"Talk1045","CNzh":"<unk[3:0:7]><unk[4:0:10 72 97 112 112 121]>都这么晚了还听我倾诉，\n真是谢谢你啊！","TWzh":"<unk[3:0:7]><unk[4:0:10 72 97 112 112 121]>都這麼晚了，你居然還願意聽我傾訴，\n真是太感謝了！","JPja":"<unk[3:0:7]><unk[4:0:10 72 97 112 112 121]>こんな<Ruby={4:6}じかん>時間なのに <Ruby={2:6}わたし>私の<Ruby={2:6}はなし>話を<Ruby={2:2}き>聞いてくれて\nありがとうございます！","USen":"<unk[3:0:7]><unk[4:0:10 72 97 112 112 121]>Thanks for lending your ear at such a\nlate hour!"},{"id":38458,"index":5,"key":"Talk1046","CNzh":"<unk[3:0:7]><unk[4:0:10 72 97 112 112 121]>从这么早就听我倾诉，\n真是谢谢你啊！","TWzh":"<unk[3:0:7]><unk[4:0:10 72 97 112 112 121]>這麼大清早，你居然還願意聽我傾訴，\n真是太感謝了！","JPja":"<unk[3:0:7]><unk[4:0:10 72 97 112 112 121]>こんな<Ruby={4:6}じかん>時間から <Ruby={2:6}わたし>私の<Ruby={2:6}はなし>話を<Ruby={2:2}き>聞いてくれて\nありがとうございます！","USen":"<unk[3:0:7]><unk[4:0:10 72 97 112 112 121]>Thanks for lending your ear at such an\nearly hour!"},{"id":38459,"index":6,"key":"Talk1047","CNzh":"<unk[3:0:7]><unk[4:0:10 72 97 112 112 121]>不顾会淋湿来听我倾诉，\n真是谢谢你啊！","TWzh":"<unk[3:0:7]><unk[4:0:10 72 97 112 112 121]>明明會淋濕，你居然還願意聽我傾訴，\n真是太感謝了！","JPja":"<unk[3:0:7]><unk[4:0:10 72 97 112 112 121]><Ruby={2:2}ぬ>濡れちゃうのに <Ruby={2:6}わたし>私の<Ruby={2:6}はなし>話を<Ruby={2:2}き>聞いてくれて\nありがとうございます！","USen":"<unk[3:0:7]><unk[4:0:10 72 97 112 112 121]>Thanks for lending your ear, even in\nweather like this!"},{"id":38460,"index":7,"key":"Talk1001","CNzh":"<unk[3:0:263]>我从这位绅士口中\n听到了令人深感兴趣的啼鸣。","TWzh":"<unk[3:0:263]>我正在向這位紳士\n打聽各方面的消息呢。","JPja":"<unk[3:0:263]><Ruby={2:4}おれ>俺の<Ruby={2:4}ほう>方は こちらのジェントリマンから\n<Ruby={4:8}いろいろ>色々 <Ruby={2:2}き>聞いていたところだ","USen":"<unk[3:0:263]>I've been hearing some interesting chirps\nand warbles..."},{"id":38461,"index":8,"key":"Talk1002","CNzh":"<unk[3:0:7]><unk[4:0:16 71 114 101 101 116 105 110 103]>啊，你也是记者吗？\n\n哎呀，真是有点不可思议的体验啊。","TWzh":"<unk[3:0:7]><unk[4:0:16 71 114 101 101 116 105 110 103]>啊，你也是記者嗎？\n\n哎呀，我經歷了一段不可思議的體驗呢。","JPja":"<unk[3:0:7]><unk[4:0:16 71 114 101 101 116 105 110 103]>ああ アナタも<Ruby={4:6}きしゃ>記者さんなのか\n\nいや ちょっと<Ruby={6:6}ふしぎ>不思議な<Ruby={4:8}たいけん>体験をしましてね","USen":"<unk[3:0:7]><unk[4:0:16 71 114 101 101 116 105 110 103]>Oh, you're also a reporter?\n\n\nI just had a bit of a strange experience\nis all."},{"id":38462,"index":9,"key":"Talk1017","CNzh":"<unk[3:0:7]>我在前面被遗迹砸到的<Color=red>三岔路口<Color=white>\n被一位<Color=red>女性<Color=white>搭话了。\n“<Color=red>那位大人<Color=white>有危险！”<PageBreak>“因为<Color=red>那位大人<Color=white>的性命正受到威胁，\n所以我不方便透露其身份，不过还请出手相救！”\n她是这么说的……","TWzh":"<unk[3:0:7]>我在前方那插著遺跡的<Color=red>三叉路附近<Color=white>，\n被一位<Color=red>女性<Color=white>搭話……\n「<Color=red>那位大人<Color=white>有危險了！」<PageBreak>「他的性命正受到威脅，所以不方便透露\n　<Color=red>那位大人<Color=white>的真實身分，不過還是請您救救他！」\n……他是這麼說的。","JPja":"<unk[3:0:7]>この<Ruby={2:4}さき>先にある <Ruby={4:6}いせき>遺跡が<Ruby={2:2}さ>刺さった<Color=red><Ruby={6:8}さんさろ>三差路の<Ruby={2:4}あた>辺り<Color=white>で<Color=red>\n<Ruby={4:8}じょせい>女性<Color=white>に<Ruby={2:4}はな>話しかけられたんです\n「<Color=red>あの<Ruby={2:4}かた>方<Color=white>が<Ruby={2:4}あぶ>危ない！」<PageBreak>「<Ruby={2:6}いのち>命を<Ruby={2:4}ねら>狙われているので\n<Color=red>あの<Ruby={2:4}かた>方<Color=white>の<Ruby={4:6}みぶん>身分は<Ruby={2:2}あ>明かせないけど<Ruby={2:4}たす>助けてほしい！」\nって…","USen":"<unk[3:0:7]>You see, I was by the debris near the\n<Color=red>three-way intersection<Color=white> up ahead when a\n<Color=red>woman <Color=white>came up to me.\n\"Please! Please, you have to help <Color=red>her<Color=white>!\n\n\n\"Her life is in danger! It would only make\nit worse to reveal who she is...\n\n\"But please, you must save <Color=red>her<Color=white>!\"<unk[5:1]>\nThat's what she said to me."},{"id":38463,"index":10,"key":"Talk1018","CNzh":"<unk[3:0:12]>我看她十分为难，\n就悄悄跟在她身后。\n可怎么追都追不上……\n\n<unk[3:0:263]>结果追到半路就跟丢了，\n再然后……就没下文了。","TWzh":"<unk[3:0:12]>我看那位女性一副很困擾的樣子，\n所以就跟在他後面走了。\n不過無論我怎麼努力，都追不上他……\n\n<unk[3:0:263]>結果在中途就跟丟對方，\n然後……就沒下文了。","JPja":"<unk[3:0:12]><Ruby={2:4}こま>困ってそうだったので\nその<Ruby={4:8}じょせい>女性の<Ruby={2:4}あと>後をついて<Ruby={2:2}い>行ったのですが\nどんなに<Ruby={4:6}がんば>頑張っても <Ruby={6:10}ぜんぜんお>全然追いつけなくて…\n\n<unk[3:0:263]><Ruby={4:10}けっきょく>結局 <Ruby={4:8}とちゅう>途中で<Ruby={4:8}みうしな>見失ってしまって\nそれっきり… だったんです","USen":"<unk[3:0:12]>The woman sounded really desperate, so\nI decided to follow her.\n\nBut no matter how hard I tried, I couldn't\nkeep up.\n\n<unk[3:0:263]>Eventually I lost track of her. <unk[5:0]>That's all\nthere is to it."},{"id":38464,"index":11,"key":"Talk1003","CNzh":"<unk[3:0:7]>喂，搭档……\n\n你觉不觉得那位女性口中的\n“<Color=red>那位大人<Color=white>”很令人在意啊……\n<unk[3:0:12]>既然不能表明身份，\n想必出身一定很高贵吧……\n而且还说有性命之忧……\n\n我脑海里不禁闪过了\n我们正在找寻的<Color=red>那位大人<Color=white>的身影啊。\n<unk[3:0:263]>搞不好真的就是她。\n\n看来这啼鸣\n值得深入一啄呢。","TWzh":"<unk[3:0:7]>我說搭檔啊……\n\n你不覺得那位女性所說的<Color=red>那位大人<Color=white>\n很令人在意嗎……\n<unk[3:0:12]>既然不能表明身分，\n代表那個人恐怕有著顯赫的身分……\n而且性命還被某些人給盯上了……\n\n令人不禁聯想到\n我們正在尋找的<Color=red>那位大人<Color=white>呢。\n<unk[3:0:263]>搞不好……搞不好真的是他……\n\n這段鳥語，\n似乎有啄食的價值呢。","JPja":"<unk[3:0:7]>なあ <Ruby={4:8}あいぼう>相棒…\n\nその<Ruby={4:8}じょせい>女性がいう <Color=red>あの<Ruby={2:4}かた>方<Color=white>ってのが\n<Ruby={2:2}ひ>引っ<Ruby={2:2}か>掛からないか…\n<unk[3:0:12]><Ruby={4:6}みぶん>身分を<Ruby={2:2}あ>明かせないって<Ruby={2:4}こと>事は\nおそらく<Ruby={4:6}こうき>高貴な<Ruby={2:2}で>出なんだろうし…\nその<Ruby={2:4}うえ>上 <Ruby={2:4}だれ>誰かに<Ruby={2:6}いのち>命を<Ruby={2:4}ねら>狙われているなんて…\n\n<Ruby={2:4}おれ>俺たちが<Ruby={2:2}お>追ってる<Color=red>あの<Ruby={2:4}かた>方<Color=white>が\n<Ruby={2:6}あたま>頭にちらつくんだよなぁ\n<unk[3:0:263]>これはひょっとすると ひょっとするかもな\n\nこのさえずり\nついばんでみる<Ruby={4:4}かち>価値はありそうだぞ","USen":"<unk[3:0:7]>Hey, partner...\n\n\nDoes something strike you as odd about\nthis person whose identity can't\nbe revealed?\n<unk[3:0:12]>And if revealing who she is to strangers\nis dangerous... Could she be someone of\ngreat importance?\nAnd if her life is already in danger...\n\n\nWell, combining these facts makes me\nwonder if this isn't actually a particular,\nimportant person who has gone missing.\n<unk[3:0:263]>I can't be sure, of course, but if there's a\nslight chance...\n\nThere's only one way for us to know for\nsure though. We'll have to peck away at\nthis news and see what the truth is!"},{"id":38465,"index":12,"key":"Talk1004","CNzh":"<unk[3:0:12]><unk[4:0:28 81 117 101 115 116 105 111 110 78 111 114 109 97 108]><Size=80>……说起来，那位女性……一直盯着我的头发看……\n那究竟……是怎么回事啊……<Size=100>","TWzh":"<unk[3:0:12]><unk[4:0:28 81 117 101 115 116 105 111 110 78 111 114 109 97 108]><Size=80>……話說回來，那位女性一直盯著我的頭髮看……\n究竟……是怎麼回事呢……<Size=100>","JPja":"<unk[3:0:12]><unk[4:0:28 81 117 101 115 116 105 111 110 78 111 114 109 97 108]><Size=80>…そういえば あの<Ruby={4:8}じょせい>女性… <Ruby={2:4}ぼく>僕の<Ruby={2:4}かみ>髪をじろじろ<Ruby={2:2}み>見てたけど\nアレ… なんだったんだろ…<Size=100>","USen":"<unk[3:0:12]><unk[4:0:28 81 117 101 115 116 105 111 110 78 111 114 109 97 108]><Size=80>...Now that I'm thinking about the whole thing again,\nwhy was that woman staring so hard at my hair?<unk[5:0]>\nHow strange.<Size=100>"},{"id":38466,"index":13,"key":"Talk1022","CNzh":"<unk[3:0:7]>我打算继续聆听\n这位绅士的啼鸣。\n为防万一，搭档你先去\n这<Color=red>前面<Color=white>的<Color=red>三岔路口<Color=white>调查一下吧。","TWzh":"<unk[3:0:7]>我打算繼續聆聽\n這位紳士的鳥語。\n為了以防萬一，搭檔你就去調查\n這<Color=red>前方<Color=white>的<Color=red>三叉路附近<Color=white>吧。","JPja":"<unk[3:0:7]><Ruby={2:4}おれ>俺は<Ruby={2:2}ひ>引き<Ruby={2:4}つづ>続き このジェントリマンの\nさえずりを<Ruby={2:2}き>聞くとするよ\n<Ruby={4:8}あいぼう>相棒は<Ruby={2:4}ねん>念のため\nこの<Color=red><Ruby={2:4}さき>先<Color=white>にある<Color=red><Ruby={6:8}さんさろ>三差路の<Ruby={2:4}あた>辺り<Color=white>を <Ruby={4:8}ちょうさ>調査してきてくれ","USen":"<unk[3:0:7]>I'm going to keep asking around and see\nwhat else I can learn from the folks here.\n\nWhy don't you head up to that <Color=red>three-way\nintersection<Color=white> and take a look around?"},{"id":38467,"index":14,"key":"Talk1044","CNzh":"<unk[3:0:12]>那位女性口中的“<Color=red>那位大人<Color=white>”和我们正在找寻的\n<Color=red>那位大人<Color=white>，我怎么想都觉得是同一个人。\n说不定我的直觉\n就是真相。\n<unk[3:0:263]>我要赌上记者的生命\n来啄一啄这啼鸣！","TWzh":"<unk[3:0:12]>那名女性所說的<Color=red>那位大人<Color=white>，和我們正在追尋的\n<Color=red>那位大人<Color=white>，我不管怎麼想都覺得是同一個人啊。\n搞不好……\n搞不好真的是他……\n<unk[3:0:263]>我要賭上我的記者生涯\n來啄食這段鳥語！","JPja":"<unk[3:0:12]><Ruby={2:4}おれ>俺はどうしても その<Ruby={4:8}じょせい>女性が<Ruby={2:2}い>言う<Color=red>あの<Ruby={2:4}かた>方<Color=white>と\n<Ruby={2:4}おれ>俺たちが<Ruby={2:2}お>追ってる<Color=red>あの<Ruby={2:4}かた>方<Color=white>が<Ruby={2:4}かさ>重なるんだよなぁ\nこれはひょっとすると\n<Ruby={4:8}ほんとう>本当にひょっとするかもな\n<unk[3:0:263]>このさえずり <Ruby={8:14}きしゃせいめい>記者生命をかけて\nついばむぞ！","USen":"<unk[3:0:12]>I have a hunch that the <Color=red>person<Color=white> that\nwoman was referring to and the <Color=red>person<Color=white>\nwe're looking for are the same.\nI can't be sure, of course, but if there's a\nslight chance, well...\n\n<unk[3:0:263]>On my honor as a reporter, I swear we\nwill peck away at this and see what the\ntruth is!"},{"id":38468,"index":15,"key":"Talk1023","CNzh":"<unk[3:0:7]><unk[4:0:14 84 114 111 117 98 108 101]>不知道该说是捉摸不定呢，还是什么……\n反正那位女性让人感觉很不可思议。","TWzh":"<unk[3:0:7]><unk[4:0:14 84 114 111 117 98 108 101]>該說是難以捉摸嗎？不知道該怎樣形容……\n總之就是有著不可思議氛圍的女性喔。","JPja":"<unk[3:0:7]><unk[4:0:14 84 114 111 117 98 108 101]>つかみどころがないというか <Ruby={2:4}なん>何というか…\nとりあえず <Ruby={6:6}ふしぎ>不思議な<Ruby={2:4}かん>感じの<Ruby={4:8}じょせい>女性でしたよ","USen":"<unk[3:0:7]><unk[4:0:14 84 114 111 117 98 108 101]>I couldn't get a read on her at all...\nExcept that she was definitely giving off\nsome strange vibes."},{"id":38469,"index":16,"key":"Talk1024","CNzh":"<unk[3:0:7]>在前面被遗迹砸到的<Color=red>三岔路口<Color=white>，\n她对我搭话说“请救救<Color=red>那位大人<Color=white>”，\n还说什么……<unk[5:1]>“性命受到威胁，\n所以身份不方便透露”。","TWzh":"<unk[3:0:7]>在前方那插著遺跡的<Color=red>三叉路附近<Color=white>，\n他向我搭話說「請您救救<Color=red>那位大人<Color=white>」。\n還說……<unk[5:1]>他的性命正受到威脅，\n所以不方便透露真實身分。","JPja":"<unk[3:0:7]>この<Ruby={2:4}さき>先にある <Ruby={4:6}いせき>遺跡が<Ruby={2:2}さ>刺さった<Color=red><Ruby={6:8}さんさろ>三差路の<Ruby={2:4}あた>辺り<Color=white>で\n「<Color=red>あの<Ruby={2:4}かた>方<Color=white>を<Ruby={2:4}たす>助けて」って<Ruby={2:4}こえ>声をかけて<Ruby={2:2}き>来たんですよ\n<Ruby={2:6}いのち>命を<Ruby={2:4}ねら>狙われているから\n<Ruby={4:6}みぶん>身分は<Ruby={2:2}あ>明かせないけど… <unk[5:1]>って","USen":"<unk[3:0:7]>She came up to me when I was by the\ndebris near the <Color=red>three-way intersection<Color=white> up\nahead and said, \"You have to help <Color=red>her<Color=white>!\"\nThen she said, \"Her life is in danger!<unk[5:0]>\nIt would only make it worse to reveal who\nshe is...\""},{"id":38470,"index":17,"key":"Talk1025","CNzh":"<unk[3:0:259]><unk[4:0:10 84 104 105 110 107]>我怎么追都追不上……\n回过神来就找不到她的身影了……\n本来我对自己的体力还算是有信心的呢。","TWzh":"<unk[3:0:259]><unk[4:0:10 84 104 105 110 107]>無論我怎麼努力，都追不上他……\n等回過神來他就消失了喔……\n我本來還對體力挺有自信的呢。","JPja":"<unk[3:0:259]><unk[4:0:10 84 104 105 110 107]>どんなに<Ruby={4:6}がんば>頑張っても<Ruby={2:2}お>追いつけなくて…\n<Ruby={2:2}き>気づいたら<Ruby={2:2}き>消えていたんですよ…\n<Ruby={4:10}たいりょく>体力には<Ruby={4:6}じしん>自信あったんですけどね","USen":"<unk[3:0:259]><unk[4:0:10 84 104 105 110 107]>I tried to follow her to help, but I just\ncouldn't keep up with her. <unk[5:1]>I lost track\nof her pretty quickly...\nAnd here I thought I was in pretty good\nshape too."},{"id":38471,"index":18,"key":"Talk1005","CNzh":"<unk[3:0:10]><unk[4:0:10 83 99 97 114 101]>呜呜……可怜的<Color=red>那位大人<Color=white>……\n要赶快去搭救……","TWzh":"<unk[3:0:10]><unk[4:0:10 83 99 97 114 101]>嗚嗚……<Color=red>那位大人<Color=white>真是太可憐了……\n得快去救他才行……","JPja":"<unk[3:0:10]><unk[4:0:10 83 99 97 114 101]>うう… おかわいそうな<Color=red>あの<Ruby={2:4}かた>方<Color=white>…\n<Ruby={2:4}はや>早く<Ruby={2:4}たす>助けてあげないと…","USen":"<unk[3:0:10]><unk[4:0:10 83 99 97 114 101]>Oooh nooo... <unk[5:0]>My poor friend... <unk[5:0]>Please,\nyou must save her..."},{"id":38472,"index":19,"key":"0002","CNzh":"没事吧？","TWzh":"你沒事吧？","JPja":"<Ruby={6:12}だいじょうぶ>大丈夫？","USen":"Are you OK?"},{"id":38473,"index":20,"key":"Talk1037","CNzh":"<unk[3:0:11]><unk[4:0:30 84 97 108 107 80 111 115 105 116 105 118 101 95 48 49]><Size=80>啊……<unk[5:1]>金……<unk[5:0]>金色头发……<unk[5:1]>\n\n<unk[3:0:3]><unk[4:0:12 83 97 100 95 48 48]><Size=100>虽然不知道您是谁，\n但能否请您助我一臂之力？\n请恕我不能透露那位大人的身份，\n<unk[3:0:266]>可对我来说很重要的<Color=red>那位大人<Color=white>\n性命受到威胁，\n正被困在某处动弹不得……\n仅凭我自己一人实在无法施救……","TWzh":"<unk[3:0:11]><unk[4:0:30 84 97 108 107 80 111 115 105 116 105 118 101 95 48 49]><Size=80>啊……<unk[5:1]>黃……<unk[5:0]>金色頭髮……<unk[5:1]>\n\n<unk[3:0:3]><unk[4:0:12 83 97 100 95 48 48]><Size=100>雖然我不知道您是誰，\n但能不能拜託您幫幫忙呢？\n由於他的性命被人盯上，\n因此不能公開<Color=red>那位大人<Color=white>的身分。\n<unk[3:0:266]>他對我來說非常重要，\n目前正被困在某處無法動彈……\n光憑我一人實在無法帶他出來……","JPja":"<unk[3:0:11]><unk[4:0:30 84 97 108 107 80 111 115 105 116 105 118 101 95 48 49]><Size=80>あ……<unk[5:1]> き… <unk[5:0]><Ruby={4:8}きんいろ>金色の<Ruby={2:4}かみ>髪…<unk[5:1]>\n\n<unk[3:0:3]><unk[4:0:12 83 97 100 95 48 48]><Size=100>どなたか <Ruby={2:4}ぞん>存じ<Ruby={2:2}あ>上げませんが\nお<Ruby={2:6}ちから>力を お<Ruby={2:2}か>貸しいただけないでしょうか？\n<Ruby={2:6}いのち>命を<Ruby={2:4}ねら>狙われているので\n<Ruby={4:6}みぶん>身分は<Ruby={2:2}あ>明かせませんが\n<unk[3:0:266]><Ruby={2:6}わたし>私の<Ruby={4:8}たいせつ>大切な <Color=red>あの<Ruby={2:4}かた>方<Color=white>が\nとある<Ruby={4:6}ばしょ>場所で <Ruby={4:6}みうご>身動きが<Ruby={2:2}と>取れない<Ruby={4:10}じょうたい>状態なんです…\n<Ruby={6:12}わたしひとり>私一人では <Ruby={2:2}つ>連れ<Ruby={2:2}だ>出すことができなくて…","USen":"<unk[3:0:11]><unk[4:0:30 84 97 108 107 80 111 115 105 116 105 118 101 95 48 49]><Size=80>B...<unk[5:1]> B...<unk[5:0]> Blond hair...<unk[5:1]>\n\n\n<unk[3:0:3]><unk[4:0:12 83 97 100 95 48 48]><Size=100>I do not know who you are, but I ask that\nyou please help me!\n\nMy poor, regal friend's life is in danger!\nI cannot reveal who she is, for that would\nonly make things worse...\n<unk[3:0:266]>She's in hiding and unable to move.\nMy <Color=red>friend<Color=white> is in such danger...\n\nPlease! I cannot help her all by myself!"},{"id":38474,"index":21,"key":"0003","CNzh":"不管她","TWzh":"不管他","JPja":"そっとしておく","USen":"..."},{"id":38475,"index":22,"key":"Talk1038","CNzh":"<unk[3:0:10]><unk[4:0:10 83 99 97 114 101]>啊……再这样下去……\n<Color=red>那位大人<Color=white>就危险了……","TWzh":"<unk[3:0:10]><unk[4:0:10 83 99 97 114 101]>啊……再這樣下去，\n<Color=red>那位大人<Color=white>就危險了……","JPja":"<unk[3:0:10]><unk[4:0:10 83 99 97 114 101]>ああ… このままでは<Color=red>あの<Ruby={2:4}かた>方<Color=white>は\nもうおしまいだわ…","USen":"<unk[3:0:10]><unk[4:0:10 83 99 97 114 101]>Oh no... I worry that time is short for\nmy <Color=red>friend<Color=white>..."},{"id":38476,"index":23,"key":"0000","CNzh":"当然！","TWzh":"當然！","JPja":"もちろん！","USen":"Let's go!"},{"id":38477,"index":24,"key":"Talk1006","CNzh":"<unk[3:0:8]><unk[4:0:16 72 97 112 112 121 95 48 49]>谢谢您！\n\n<Color=red>那位大人<Color=white>正躲在某处，\n以防被歹徒发现。","TWzh":"<unk[3:0:8]><unk[4:0:16 72 97 112 112 121 95 48 49]>謝謝您！\n\n為了不讓<Color=red>那位大人<Color=white>被惡徒發現，\n我請他躲在了某個地方。","JPja":"<unk[3:0:8]><unk[4:0:16 72 97 112 112 121 95 48 49]>ありがとうございます！\n\n<Color=red>あの<Ruby={2:4}かた>方<Color=white>は<Ruby={4:8}わるもの>悪者に<Ruby={2:2}み>見つからぬよう\nとある<Ruby={4:6}ばしょ>場所に<Ruby={2:4}かく>隠れていただいております","USen":"<unk[3:0:8]><unk[4:0:16 72 97 112 112 121 95 48 49]>Oh, thank you so much!\n\n\nMy friend is in hiding right now. That is\nthe only way for her to remain undetected\nby those with ill intent!"},{"id":38478,"index":25,"key":"Talk1028","CNzh":"<unk[3:0:7]>我们前去的时候要避人耳目，\n先离开这里吧。","TWzh":"<unk[3:0:7]>待會得一邊避人耳目一邊前去找他，\n總之先離開這裡。","JPja":"<unk[3:0:7]><Ruby={4:6}ひとめ>人目を<Ruby={2:2}さ>避けながら<Ruby={2:2}む>向かいますので\nまずは ここから<Ruby={2:4}はな>離れましょう","USen":"<unk[3:0:7]>We should go to where my friend is... But!<unk[5:0]>\nBe careful not to be seen. We do not want\nto draw evil to her!"},{"id":38479,"index":26,"key":"Talk1062","CNzh":"<unk[3:0:7]>我就在这条<Color=red>道路的尽头<Color=white>等您，\n我们在那里会合吧。","TWzh":"<unk[3:0:7]>我會在這條<Color=red>道路前方<Color=white>等你，\n我們就在那會合吧。","JPja":"<unk[3:0:7]><Ruby={2:6}わたし>私はこの<Color=red><Ruby={4:8}かいどう>街道の<Ruby={2:4}さき>先<Color=white>で<Ruby={2:2}ま>待っていますので\nそこで<Ruby={2:2}お>落ち<Ruby={2:2}あ>合いましょう","USen":"<unk[3:0:7]>I will wait for you <Color=red>down this road<Color=white>. Meet me\nas soon as you can!"},{"id":38480,"index":27,"key":"0001","CNzh":"现在不太方便……","TWzh":"現在不太方便……","JPja":"<Ruby={2:4}いま>今はちょっと…","USen":"Not right now..."},{"id":38481,"index":28,"key":"Talk1026","CNzh":"<unk[3:0:10]><unk[4:0:12 83 97 100 95 48 49]><Color=red>那位大人<Color=white>说过……\n<Color=red>金色头发的男性<Color=white>肯定没问题……\n啊……再这样下去，\n<Color=red>那位大人<Color=white>就危险了……","TWzh":"<unk[3:0:10]><unk[4:0:12 83 97 100 95 48 49]><Color=red>那位大人<Color=white>曾說過……\n如果是<Color=red>金髮男性<Color=white>的話，肯定沒問題……\n啊……再這樣下去，\n<Color=red>那位大人<Color=white>就危險了……","JPja":"<unk[3:0:10]><unk[4:0:12 83 97 100 95 48 49]><Color=red><Ruby={4:8}きんいろ>金色の<Ruby={2:4}かみ>髪の<Ruby={4:8}だんせい>男性<Color=white>ならきっと<Ruby={6:12}だいじょうぶ>大丈夫だと\n<Color=red>あの<Ruby={2:4}かた>方<Color=white>がおっしゃっていたのですが…\nああ… このままでは<Color=red>あの<Ruby={2:4}かた>方<Color=white>は\nもうおしまいだわ…","USen":"<unk[3:0:10]><unk[4:0:12 83 97 100 95 48 49]>She told me that, so long as the one who\ncame to her aid was <Color=red>a man with blond\nhair<Color=white>, she was sure to be OK.\nOh no... I worry that time is short for\nmy <Color=red>friend<Color=white>..."},{"id":38482,"index":29,"key":"Talk1027","CNzh":"<unk[3:0:7]>金色头发的大人！\n我坚信您一定会回来的！\n<unk[3:0:3]>但是……我们在这里拖延的时候，\n<Color=red>那位大人<Color=white>就……\n<Color=red>我带您去那位大人<Color=white>的所在之处，\n请跟着我走好吗？","TWzh":"<unk[3:0:7]>金髮的先生！\n我就知道您一定會回來的！\n<unk[3:0:3]>但是……在我們像這樣對話的期間，\n<Color=red>那位大人<Color=white>也……\n我來<Color=red>帶領<Color=white>您去找<Color=red>那位大人<Color=white>，\n可以請您跟著我嗎？","JPja":"<unk[3:0:7]><Ruby={4:8}きんいろ>金色の<Ruby={2:4}かみ>髪の<Ruby={2:4}かた>方！\nきっと<Ruby={2:4}もど>戻ってきてくださると<Ruby={2:4}しん>信じていました！\n<unk[3:0:3]>でも… こうしている<Ruby={2:6}あいだ>間にも\n<Color=red>あの<Ruby={2:4}かた>方<Color=white>は…\n<Color=red>あの<Ruby={2:4}かた>方<Color=white>の<Ruby={2:6}ところ>所に<Color=red>ご<Ruby={4:8}あんない>案内<Color=white>しますので\n<Ruby={2:6}わたし>私についてきていただけますか？","USen":"<unk[3:0:7]>Oh, it is the blond-haired man! I knew\nthat you would return to help...\n\n<unk[3:0:3]>But we cannot remain here! My poor,\nregal <Color=red>friend<Color=white>...\n\nI shall guide you to where <Color=red>she<Color=white> is hiding.\nWill you follow me?"},{"id":38483,"index":30,"key":"Talk1049","CNzh":"<unk[3:0:11]><unk[4:0:24 83 117 114 112 114 105 115 101 83 95 48 49]>啊，竟然弄得这么湿……","TWzh":"<unk[3:0:11]><unk[4:0:24 83 117 114 112 114 105 115 101 83 95 48 49]>啊……您居然濕成這樣……","JPja":"<unk[3:0:11]><unk[4:0:24 83 117 114 112 114 105 115 101 83 95 48 49]>ああ そんなに<Ruby={2:2}ぬ>濡れてしまって…","USen":"<unk[3:0:11]><unk[4:0:24 83 117 114 112 114 105 115 101 83 95 48 49]>Oh my, you are drenched."},{"id":38484,"index":31,"key":"Talk1007","CNzh":"<unk[3:0:3]><unk[4:0:6 83 97 100]>非常抱歉扔下您不顾，\n但我很担心<Color=red>那位大人<Color=white>……<unk[5:1]>\n<unk[3:0:263]><Color=red>那位大人<Color=white>就在\n避人耳目的地方休息，\n路有些难走，不好意思……","TWzh":"<unk[3:0:3]><unk[4:0:6 83 97 100]>將您放著不管真的十分抱歉。\n因為我太擔心<Color=red>那位大人<Color=white>了……<unk[5:1]>\n<unk[3:0:263]><Color=red>那位大人<Color=white>正在一個\n避人耳目的地方休息。\n不好意思，前去的路途會有點險峻……","JPja":"<unk[3:0:3]><unk[4:0:6 83 97 100]><Ruby={2:2}お>置いてきぼりにして<Ruby={2:4}もう>申し<Ruby={2:4}わけ>訳ありません\n<Color=red>あの<Ruby={2:4}かた>方<Color=white>が<Ruby={4:8}しんぱい>心配で…<unk[5:1]>\n<unk[3:0:263]><Color=red>あの<Ruby={2:4}かた>方<Color=white>は <Ruby={4:6}ひとめ>人目を<Ruby={2:2}さ>避ける<Ruby={4:6}ばしょ>場所で\n<Ruby={2:4}やす>休んでおられます\n<Ruby={2:4}すこ>少し<Ruby={4:6}あくろ>悪路で<Ruby={2:4}もう>申し<Ruby={2:4}わけ>訳ありませんが…","USen":"<unk[3:0:3]><unk[4:0:6 83 97 100]>My apologies for leaving you behind. I was\novertaken by my concern for my <Color=red>friend<Color=white>...\n\n<unk[3:0:263]><Color=red>She<Color=white> is resting safely out of sight. It is\nthe only way to stay safe.\n\nI am sorry that the path is so poor..."},{"id":38485,"index":32,"key":"Talk1034","CNzh":"<unk[3:0:7]>能麻烦您到\n那边的<Color=red>悬崖上<Color=white>去吗？","TWzh":"<unk[3:0:7]>能麻煩您到\n那邊的<Color=red>山崖上<Color=white>嗎？","JPja":"<unk[3:0:7]>あの<Color=red><Ruby={2:4}がけ>崖の<Ruby={2:4}うえ>上<Color=white>まで\nお<Ruby={2:2}こ>越しいただけますでしょうか？","USen":"<unk[3:0:7]>Could you possibly go to the <Color=red>top of\nthat cliff<Color=white>?"},{"id":38486,"index":33,"key":"Talk1063","CNzh":"<unk[3:0:7]>我们就在\n<Color=red>地上插着坠落物<Color=white>的地方会合吧！","TWzh":"<unk[3:0:7]>我們就在地上插著\n<Color=red>掉落物<Color=white>的地方會合吧。","JPja":"<unk[3:0:7]>ちょうど<Color=red><Ruby={6:10}らっかぶつ>落下物<Color=white>が<Ruby={2:2}さ>刺さっている\n<Ruby={2:4}あた>辺りで<Ruby={2:2}お>落ち<Ruby={2:2}あ>合いましょう！","USen":"<unk[3:0:7]>We can meet right where you can see the\n<Color=red>fallen debris<Color=white>!"},{"id":38487,"index":34,"key":"Talk1050","CNzh":"<unk[3:0:1]><unk[4:0:16 72 97 112 112 121 95 48 48]>雨天路滑，\n您竟然愿意赶路至此……","TWzh":"<unk[3:0:1]><unk[4:0:16 72 97 112 112 121 95 48 48]>在天雨路滑的狀況下，\n您居然還願意來到這裡……","JPja":"<unk[3:0:1]><unk[4:0:16 72 97 112 112 121 95 48 48]><Ruby={2:4}あめ>雨で<Ruby={2:4}すべ>滑りやすい<Ruby={2:4}なか>中\nここまで<Ruby={2:2}き>来ていただけるなんて","USen":"<unk[3:0:1]><unk[4:0:16 72 97 112 112 121 95 48 48]>I am sorry that you had to travel so far\nwith everything so slippery from the rain..."},{"id":38488,"index":35,"key":"Talk1011","CNzh":"<unk[3:0:1]><unk[4:0:18 76 97 117 103 104 83 95 48 48]><Size=80>果然……<unk[5:1]><Size=100>\n\n<unk[3:0:264]>啊，失礼了，\n非常感谢您能过来！\n来吧，很快就到\n<Color=red>那位大人<Color=white>的所在之处了。","TWzh":"<unk[3:0:1]><unk[4:0:18 76 97 117 103 104 83 95 48 48]><Size=80>果然……<unk[5:1]><Size=100>\n\n<unk[3:0:264]>啊，失禮了。\n謝謝您願意過來！\n來吧，距離<Color=red>那位大人<Color=white>待的地方\n已經很近了。","JPja":"<unk[3:0:1]><unk[4:0:18 76 97 117 103 104 83 95 48 48]><Size=80>…やはり<unk[5:1]><Size=100>\n\n<unk[3:0:264]>あ <Ruby={4:8}しつれい>失礼しました\n<Ruby={2:2}き>来てくれてありがとうございます！\nさあ <Color=red>あの<Ruby={2:4}かた>方<Color=white>のいらっしゃる<Ruby={4:6}ばしょ>場所は\nもうすぐです","USen":"<unk[3:0:1]><unk[4:0:18 76 97 117 103 104 83 95 48 48]><Size=80>It must be him, then...<unk[5:1]><Size=100>\n\n\n<unk[3:0:264]>Oh, I am so rude! You have my apologies!\n\n\nCome now! My <Color=red>friend<Color=white> is waiting ahead!"},{"id":38489,"index":36,"key":"Talk1012","CNzh":"<unk[3:0:7]><Color=red>那位大人<Color=white>的所在之处\n就在<Color=red>对面坠落物<Color=white>的附近。\n我先走一步，\n去向<Color=red>那位大人<Color=white>报告您的事情。","TWzh":"<unk[3:0:7]><Color=red>那位大人<Color=white>待的地方就在\n<Color=red>對面掉落物<Color=white>的附近。\n那麼我就先走一步\n向<Color=red>那位大人<Color=white>報告您的事了。","JPja":"<unk[3:0:7]><Color=red>あの<Ruby={2:4}かた>方<Color=white>のいらっしゃる<Ruby={4:6}ばしょ>場所は\n<Color=red><Ruby={2:2}む>向こう<Ruby={2:4}ぎし>岸の<Ruby={4:6}らっか>落下<Ruby={2:4}ぶつ>物<Color=white>がある<Ruby={2:4}あた>辺りです\n<Ruby={2:6}わたし>私は<Ruby={4:8}ひとあし>一足お<Ruby={2:4}さき>先に <Color=red>あの<Ruby={2:4}かた>方<Color=white>に\nアナタのことを<Ruby={4:8}ほうこく>報告してまいります","USen":"<unk[3:0:7]>She is waiting nearby, around the\n<Color=red>debris on the opposite cliff<Color=white>.\n\nI will go on ahead and let <Color=red>her<Color=white> know that\nyou are coming!"},{"id":38490,"index":37,"key":"Talk1039","CNzh":"<unk[3:0:1]><unk[4:0:12 76 97 117 103 104 83]>虽然距离有点远，\n但我坚信您一定会来的。","TWzh":"<unk[3:0:1]><unk[4:0:12 76 97 117 103 104 83]>雖然還有點距離，\n但我相信您一定能抵達的。","JPja":"<unk[3:0:1]><unk[4:0:12 76 97 117 103 104 83]>ちょっと<Ruby={2:4}はな>離れていますが\nアナタならきっと<Ruby={2:2}き>来てくれると<Ruby={2:4}しん>信じています","USen":"<unk[3:0:1]><unk[4:0:12 76 97 117 103 104 83]>It is a bit far off, but I know you will be\nable to make it!"},{"id":38491,"index":38,"key":"Talk1015","CNzh":"<unk[3:0:7]>非常抱歉做出了\n试探您的行为，\n金色头发……\n加上跨越任何道路的力量和勇气，\n还有胜过一切的伪善面貌……\n\n<unk[3:0:263]>您就是塞尔达公主的\n随行剑士林克本人没错吧。","TWzh":"<unk[3:0:7]>很抱歉做出這些\n像是在試探您的行為。\n金髮……\n而且擁有跨越任何障礙的力量及勇氣。\n其中最明顯的就是那副偽善的樣子……\n\n<unk[3:0:263]>您果然就是薩爾達公主的\n親衛劍士林克。","JPja":"<unk[3:0:7]>アナタを<Ruby={2:4}ため>試すようなことをして\n<Ruby={2:4}もう>申し<Ruby={2:4}わけ>訳ありません\n<Ruby={4:8}きんいろ>金色の<Ruby={2:4}かみ>髪…\nそして どんな<Ruby={2:4}みち>道も<Ruby={2:2}の>乗り<Ruby={2:2}こ>越える<Ruby={2:6}ちから>力と<Ruby={4:6}ゆうき>勇気\nそれに<Ruby={2:4}なに>何より<Ruby={4:6}ぎぜん>偽善ぶり…\n\n<unk[3:0:263]>アナタは ゼルダ<Ruby={2:4}ひめ>姫お<Ruby={2:2}つ>付きの <Ruby={4:6}けんし>剣士リンク\n<Ruby={4:8}ほんにん>本人で<Ruby={4:6}まちが>間違いありませんね","USen":"<unk[3:0:7]>I am sorry for all of that. It was important\nfor me to test you.\n\nBlond hair, courage to overcome a\nchallenge. And then another challenge.\nAnd then another!\nOh, and your disgusting, unwavering\ncommitment to do \"good.\"\n\n<unk[3:0:263]>You are Princess Zelda's chosen\nbodyguard, the swordsman Link, correct?"},{"id":38492,"index":39,"key":"Talk1035","CNzh":"<unk[3:0:8]><unk[4:0:18 76 97 117 103 104 83 95 48 48]>呵呵，终于见面了呢……\n那么我来带您去最后的地方吧。\n那就是……","TWzh":"<unk[3:0:8]><unk[4:0:18 76 97 117 103 104 83 95 48 48]>呵呵，總算見到您了……\n那麼就帶您前往最後的地點吧。\n目的地就是……","JPja":"<unk[3:0:8]><unk[4:0:18 76 97 117 103 104 83 95 48 48]>ふふ とうとう<Ruby={4:4}であ>出会えたわ…\nでは<Ruby={4:6}さいご>最後の<Ruby={4:6}ばしょ>場所にお<Ruby={2:2}つ>連れしましょう\n<Ruby={2:2}い>行き<Ruby={2:4}さき>先は……","USen":"<unk[3:0:8]><unk[4:0:18 76 97 117 103 104 83 95 48 48]>Hehehe, I am so glad to finally meet you.\nNow I can take you to the last stop in our\nlittle journey."},{"id":38493,"index":40,"key":"Talk1016","CNzh":"<unk[3:0:8]><unk[4:0:18 76 97 117 103 104 76 95 48 49]>地狱～！<unk[1:3:90 0]>","TWzh":"<unk[3:0:8]><unk[4:0:18 76 97 117 103 104 76 95 48 49]>地獄喔～<unk[1:3:90 0]>","JPja":"<unk[3:0:8]><unk[4:0:18 76 97 117 103 104 76 95 48 49]><Ruby={4:6}じごく>地獄となりま～す<unk[1:3:90 0]>","USen":"<unk[3:0:8]><unk[4:0:18 76 97 117 103 104 76 95 48 49]>Your grave! Haha!<unk[1:3:90 0]>"},{"id":38494,"index":41,"key":"Talk1059","CNzh":"<unk[3:0:263]><unk[4:0:22 71 114 101 101 116 105 110 103 95 48 48]>站住，林克！\n我可不会放你离开这里！","TWzh":"<unk[3:0:263]><unk[4:0:22 71 114 101 101 116 105 110 103 95 48 48]>站住，林克！\n我不會讓你逃出這裡！","JPja":"<unk[3:0:263]><unk[4:0:22 71 114 101 101 116 105 110 103 95 48 48]><Ruby={2:2}ま>待て リンク！\nこの<Ruby={2:2}ば>場からは <Ruby={2:2}に>逃がさんぞ！","USen":"<unk[3:0:263]><unk[4:0:22 71 114 101 101 116 105 110 103 95 48 48]>It's no use, Link! I won't let you escape!"},{"id":38495,"index":42,"key":"Talk1061","CNzh":"<unk[3:0:7]><unk[4:0:16 84 105 114 101 100 95 48 48]>这……<unk[5:1]>这次就先放你一马。\n\n<unk[3:0:265]>不过记住，下次就没这等好事了！\n你给我洗干净脖子等着吧！","TWzh":"<unk[3:0:7]><unk[4:0:16 84 105 114 101 100 95 48 48]>這……<unk[5:1]>這次就先放過你。\n\n<unk[3:0:265]>不過給我記好，我下次絕不會饒了你！\n做好心理準備吧！","JPja":"<unk[3:0:7]><unk[4:0:16 84 105 114 101 100 95 48 48]>こ… <unk[5:1]><Ruby={4:8}こんかい>今回はこのぐらいで<Ruby={2:4}ゆる>許してやろう \n\n<unk[3:0:265]>だがしかし <Ruby={2:4}つぎ>次は<Ruby={4:8}ようしゃ>容赦はせぬ！\n<Ruby={4:6}かくご>覚悟しておくんだな","USen":"<unk[3:0:7]><unk[4:0:16 84 105 114 101 100 95 48 48]>I'll...<unk[5:1]> I'll let you off this time.\n\n\n<unk[3:0:265]>But don't expect such mercy next time.<unk[5:0]>\nPrepare yourself!"},{"id":38496,"index":43,"key":"Talk1056","CNzh":"<unk[3:0:7]><unk[4:0:14 67 97 108 108 70 97 114]>喂～！<unk[5:0]>搭档～！","TWzh":"<unk[3:0:7]><unk[4:0:14 67 97 108 108 70 97 114]>喂～！<unk[5:0]>搭檔～！","JPja":"<unk[3:0:7]><unk[4:0:14 67 97 108 108 70 97 114]>お～い！<unk[5:0]> <Ruby={4:8}あいぼう>相棒～！","USen":"<unk[3:0:7]><unk[4:0:14 67 97 108 108 70 97 114]>Hey!<unk[5:0]> Hey, partner!"},{"id":38497,"index":44,"key":"Talk1057","CNzh":"<unk[3:0:7]><unk[4:0:34 81 117 101 115 116 105 111 110 78 111 114 109 97 108 95 48 48]>原来你在这里……<unk[5:0]>\n你跑到这么远的地方来调查啊。\n我是刚好在上空调查\n神秘女性邀请前往的地点……\n突然听到说话声便过来看看，\n然后就看到了搭档你。","TWzh":"<unk[3:0:7]><unk[4:0:34 81 117 101 115 116 105 111 110 78 111 114 109 97 108 95 48 48]>原來你在這種地方……<unk[5:0]>\n你為了調查跑到這麼遠的地方來啊。\n我剛好在上空調查傳聞中\n有神秘女子出沒向人提出邀請的地點……\n突然聽到有人的聲音就過來看看了，\n然後就遇見搭檔你啦。","JPja":"<unk[3:0:7]><unk[4:0:34 81 117 101 115 116 105 111 110 78 111 114 109 97 108 95 48 48]>こんな<Ruby={2:6}ところ>所にいたのか…<unk[5:0]>\nずいぶん<Ruby={2:4}とお>遠くまで<Ruby={4:8}ちょうさ>調査していたようだな\n<Ruby={2:4}おれ>俺は <Ruby={2:4}なぞ>謎の<Ruby={2:6}おんな>女がいざなっていたという<Ruby={4:6}ばしょ>場所を\n<Ruby={4:10}じょうくう>上空から<Ruby={2:4}しら>調べていたんだが…\nふと <Ruby={2:4}ひと>人の<Ruby={2:4}こえ>声のする<Ruby={2:4}ほう>方に<Ruby={2:2}き>来てみたら\n<Ruby={4:8}あいぼう>相棒の<Ruby={2:6}すがた>姿を<Ruby={2:2}み>見かけてな","USen":"<unk[3:0:7]><unk[4:0:34 81 117 101 115 116 105 111 110 78 111 114 109 97 108 95 48 48]>So this is where your investigation took\nyou. Looks like you really got yourself out\non a limb there!\nI've been scouting from the skies, trying\nto get to the bottom of this story. I heard\nthat woman was luring people away...\nI thought I heard her voice, so I swooped\non down. And, hey, here you are!"},{"id":38498,"index":45,"key":"Talk1054","CNzh":"<unk[3:0:263]>……所以你啄到了些什么？","TWzh":"<unk[3:0:263]>……所以，你有啄食到什麼了嗎？","JPja":"<unk[3:0:263]>…で <Ruby={2:4}なに>何かついばめたかい？","USen":"<unk[3:0:263]>So tell me...<unk[5:0]> What have you unearthed?"},{"id":38499,"index":46,"key":"Talk1019","CNzh":"<unk[3:0:11]>什么？？\n那……<unk[5:1]>那竟然是依盖队的陷阱？\n他们是企图\n毁灭海拉鲁王国的暗杀集团……\n<unk[3:0:268]>我听说过他们很擅长乔装，\n但没想到居然会假扮成村民，\n试图刺杀公主殿下的\n随行剑士大人……","TWzh":"<unk[3:0:11]>什麼？？\n你……<unk[5:1]>你說那是依蓋隊設下的陷阱？\n那些傢伙是試圖顛覆海拉魯王國的\n暗殺者集團……\n<unk[3:0:268]>雖然聽說過他們很擅長變裝，\n不過我沒想到會打扮成村民的樣子，\n意圖謀害公主殿下的\n親衛劍士大人啊……","JPja":"<unk[3:0:11]>なんだって？？\nイ…<unk[5:1]> イーガ<Ruby={2:4}だん>団の<Ruby={2:4}わな>罠だったって？\nアイツラは ハイラル<Ruby={4:8}おうこく>王国を\n<Ruby={2:4}ほろ>滅ぼそうとしている <Ruby={10:22}あんさつしゃしゅうだん>暗殺者集団…\n<unk[3:0:268]><Ruby={4:8}へんそう>変装が<Ruby={4:6}とくい>得意 って<Ruby={2:6}はなし>話は<Ruby={2:2}き>聞いていたが\nまさか <Ruby={4:8}むらびと>村人に<Ruby={2:6}すがた>姿を<Ruby={2:2}か>変えて\n<Ruby={4:8}ひめさま>姫様お<Ruby={2:2}つ>付きの<Ruby={6:10}けんしさま>剣士様の<Ruby={2:6}いのち>命を\n<Ruby={2:4}ねら>狙おうとしてたとはな…","USen":"<unk[3:0:11]>I see... <unk[5:0]>Who could have guessed that this\nwhole story would be an elaborate trap\nset by the <Color=red>Yiga Clan<Color=white>...\nIf you didn't know, they're a group of\nassassins trying to bring down the\nkingdom of Hyrule.\n<unk[3:0:268]>I heard they were good at disguising\nthemselves,<unk[5:0]> but playing the part of a\nvillager? I never would have guessed.\nAnd all to flush out the swordsman who\nprotects the princess..."},{"id":38500,"index":47,"key":"Talk1060","CNzh":"<unk[3:0:11]>什么？？\n那位发出邀请的女性<unk[5:1]>竟然是依盖队的？\n<unk[3:0:268]>没想到他们竟然假扮成村民\n试图找出公主殿下的\n随行剑士大人……\n\n<unk[3:0:264]><unk[4:0:10 72 97 112 112 121]>而且搭档你几次三番被错认为剑士大人，\n还真是多灾多难啊。","TWzh":"<unk[3:0:11]>你說什麼？？\n向人提出邀請的女子，<unk[5:1]>其實是依蓋隊的成員？\n<unk[3:0:268]>沒想到他們會為了引出\n公主殿下的親衛劍士大人，\n而特意假扮成村民的樣子啊……\n\n<unk[3:0:264]><unk[4:0:10 72 97 112 112 121]>不過搭檔你好幾次都被誤認成劍士大人，\n真是多災多難呢。","JPja":"<unk[3:0:11]>なんだって？？\nいざなう<Ruby={2:6}おんな>女は<unk[5:1]> イーガ<Ruby={2:4}だん>団だったってのか？\n<unk[3:0:268]>まさか <Ruby={4:8}むらびと>村人に<Ruby={2:6}すがた>姿を<Ruby={2:2}か>変えて\n<Ruby={4:8}ひめさま>姫様お<Ruby={2:2}つ>付きの<Ruby={6:10}けんしさま>剣士様を\nあぶりだそうとしてたとはな…\n\n<unk[3:0:264]><unk[4:0:10 72 97 112 112 121]>しっかし <Ruby={4:8}あいぼう>相棒も<Ruby={4:6}なんど>何度も<Ruby={4:6}まちが>間違われて\nトんだ <Ruby={4:8}さいなん>災難だったな\n","USen":"<unk[3:0:11]>What's that?<unk[5:1]> The woman who was asking\nfor help was actually a member of the\nYiga Clan?\n<unk[3:0:268]>So she disguised herself as a villager\nand was trying to lure the princess's\nappointed knight to a trap...\n<unk[3:0:264]><unk[4:0:10 72 97 112 112 121]>It really is some impressively bad luck\nthat they keep coming after you instead,\nisn't it?"},{"id":38501,"index":48,"key":"Talk1020","CNzh":"<unk[3:0:8]><unk[4:0:10 72 97 112 112 121]>不过只因为金色头发\n就被错认为剑士大人，\n还真是灾难啊。","TWzh":"<unk[3:0:8]><unk[4:0:10 72 97 112 112 121]>話說回來，居然只是因為一頭金髮\n就被誤認為劍士大人……\n真是飛來橫禍啊。","JPja":"<unk[3:0:8]><unk[4:0:10 72 97 112 112 121]>にしても よりによって <Ruby={4:8}きんいろ>金色の<Ruby={2:4}かみ>髪ってだけで\n<Ruby={6:10}けんしさま>剣士様に<Ruby={4:6}まちが>間違えられるなんて\nトんだ <Ruby={4:8}さいなん>災難だったな","USen":"<unk[3:0:8]><unk[4:0:10 72 97 112 112 121]>They thought you, a young up-and-\ncoming reporter who just happens\nto have blond hair...\nThey believed you were actually that\nswordsman? <unk[5:1]>That's just bad luck for you!"},{"id":38502,"index":49,"key":"Talk1058","CNzh":"<unk[3:0:257]>搭档你竟然击退了那个依盖队，身手真不错啊！\n我这个做前辈的也很自豪呢！","TWzh":"<unk[3:0:257]>搭檔你居然能擊退那個依蓋隊，身手真不錯啊！\n連我這個前輩都感到很驕傲呢！","JPja":"<unk[3:0:257]><Ruby={4:8}あいぼう>相棒も あのイーガ<Ruby={2:4}だん>団を<Ruby={2:6}しりぞ>退けちまうなんて\n<Ruby={2:4}たい>大した<Ruby={4:8}うでまえ>腕前だな <Ruby={4:8}せんぱい>先輩の<Ruby={2:4}おれ>俺も<Ruby={2:4}はな>鼻が<Ruby={2:4}たか>高いぜ","USen":"<unk[3:0:257]>You've definitely got some skills, though,\nif you can escape from the Yiga Clan.<unk[5:0]>\nI'm proud of you, partner."},{"id":38503,"index":50,"key":"Talk1021","CNzh":"<unk[3:0:257]>不用落到写“新人记者倒于依盖队狂剑下”\n这种报道的境地，真是太好了。","TWzh":"<unk[3:0:257]>「新人記者，殞於依蓋隊狂劍之下」……\n好險事態沒有演變成需要寫這種報導的情況。","JPja":"<unk[3:0:257]>『<Ruby={12:22}しんまいしんぶんきしゃ>新米新聞記者 イーガ<Ruby={2:4}だん>団の<Ruby={4:10}きょうけん>狂剣に<Ruby={2:4}たお>倒れる』\nなんて<Ruby={4:4}きじ>記事 <Ruby={2:2}か>書く<Ruby={4:4}はめ>羽目にならなくてよかったよ","USen":"<unk[3:0:257]>I'm glad I don't have to write a headline\nlike, \"Junior Reporter Falls to the Cruel\nBlade of the Yiga in Pursuit of Truth!\""},{"id":38504,"index":51,"key":"Talk1032","CNzh":"<unk[3:0:263]>好了，我要赶快把这次的啼鸣\n写成报道。<unk[5:2]>那么，搭档……","TWzh":"<unk[3:0:263]>好，那麼我要趕緊將這次的鳥語寫成報導了。<unk[5:2]>\n再見啦，搭檔。","JPja":"<unk[3:0:263]>さ <Ruby={2:4}おれ>俺は<Ruby={4:8}こんかい>今回のさえずりを\nさっそく<Ruby={4:4}きじ>記事にするとしようかな <unk[5:0]>じゃあな<Ruby={4:8}あいぼう>相棒 ","USen":"<unk[3:0:263]>Anyway, it's time I took off and turned\nthese unusual details into an article.<unk[5:1]>\nYou take care, partner!"},{"id":38505,"index":52,"key":"Talk1055","CNzh":"<unk[3:0:8]><unk[4:0:14 71 111 111 100 98 121 101]><Size=125>回见鸟！<Size=100>","TWzh":"<unk[3:0:8]><unk[4:0:14 71 111 111 100 98 121 101]><Size=125>再會鳥！<Size=100>","JPja":"<unk[3:0:8]><unk[4:0:14 71 111 111 100 98 121 101]><Size=125>サラバード！<Size=100>","USen":"<unk[3:0:8]><unk[4:0:14 71 111 111 100 98 121 101]><Size=125>Soar long!<Size=100><unk[5:1]>"},{"id":38506,"index":53,"key":"near0001","CNzh":"在这边。","TWzh":"在這邊。","JPja":"こちらです","USen":"Over here."},{"id":38507,"index":54,"key":"near0004","CNzh":"果然只能到这里……","TWzh":"果然來到了這裡……","JPja":"やはりここまでは…","USen":"Was it here?"},{"id":38508,"index":55,"key":"near0005","CNzh":"那位大人在这边！","TWzh":"那位大人在這邊喔！","JPja":"あの<Ruby={2:4}かた>方は こちらですよ！","USen":"This way!"},{"id":38509,"index":56,"key":"near0002","CNzh":"多么奇妙……","TWzh":"真是奇妙……","JPja":"<Ruby={2:4}なん>何と<Ruby={4:10}ちんみょう>珍妙な…","USen":"That IS strange..."},{"id":38510,"index":57,"key":"near0006","CNzh":"来人啊……","TWzh":"快來人啊……","JPja":"<Ruby={2:4}だれ>誰か…","USen":"Someone..."}]}