{"meta":{"version":"121","folder":"EventFlowMsg","file":"IchikaraChallenge01","chunk":1,"start":100,"count":77,"total":177},"rows":[{"id":14039,"index":100,"key":"TerrorImpulse_00","CNzh":"这是什么东西！","TWzh":"這是什麼東西！","JPja":"<Ruby={2:4}なん>何だこれは！","USen":"What is this?!"},{"id":14040,"index":101,"key":"TerrorImpulse_01","CNzh":"什么都看不见……","TWzh":"什麼都看不見……","JPja":"<Ruby={2:4}なに>何も<Ruby={2:2}み>見えない…","USen":"It's blocking my view!"},{"id":14041,"index":102,"key":"TerrorImpulse_02","CNzh":"什么时候堆了这东西……","TWzh":"什麼時候多了這種東西……","JPja":"いつの<Ruby={2:2}ま>間にこんなものが…","USen":"How did it even get there?"},{"id":14042,"index":103,"key":"Talk_0087","CNzh":"<unk[3:0:9]>这、这是什么东西！\n这样我都看不到前面了啊！","TWzh":"<unk[3:0:9]>這、這是什麼東西！\n這樣一來不就看不到前面了嗎！","JPja":"<unk[3:0:9]>な なんだこれは！<unk[5:0]>\nこれじゃあ <Ruby={2:4}まえ>前がみえないじゃないか！","USen":"<unk[3:0:9]>Wh-what is this?! It's right in my way.\nCan't see a thing..."},{"id":14043,"index":104,"key":"Talk_0092","CNzh":"<unk[3:0:7]>这样就好了……<PageBreak>收拾这些的劳务费，\n之后得跟松达先生要一下。","TWzh":"<unk[3:0:7]>好，這樣就行了……<PageBreak>之後得再和松達先生\n申請一下處理費啊。","JPja":"<unk[3:0:7]>これでよしっと…<PageBreak><Ruby={4:6}かたづ>片付けの<Ruby={6:8}てまちん>手間賃も\nあとでエノキダさんに<Ruby={4:10}せいきゅう>請求しないとな","USen":"<unk[3:0:7]>That ought to do it.<PageBreak>You can bet I'll be sending a bill to\nHudson for cleaning up that mess."},{"id":14044,"index":105,"key":"Near_0014","CNzh":"嗯……","TWzh":"唔……","JPja":"うーん…","USen":"Hm..."},{"id":14045,"index":106,"key":"Near_0013","CNzh":"唔～下雨了达～","TWzh":"唔～下雨了達～","JPja":"う～ <Ruby={2:4}あめ>雨なのダ～","USen":"Ugh, it's raining."},{"id":14046,"index":107,"key":"Talk_0113","CNzh":"<unk[3:0:7]>啊，大哥哥也来了达！\n爸爸一直在那里“嗯——”，好奇怪达。","TWzh":"<unk[3:0:7]>啊，大哥哥你也來了達！\n爸爸他一直「唔～唔～」地呻吟著，好奇怪達。","JPja":"<unk[3:0:7]>あっ お<Ruby={2:4}にい>兄さんも<Ruby={2:2}き>来たのダ！<unk[5:0]>\nパァパが うーんうーん うなって<Ruby={2:4}へん>変なのダ","USen":"<unk[3:0:7]>Hey! You didn't ment-son you were\ncoming here too, mister!\n\nIt's strange... Papa keeps mumbling to\nhimself, \"hmm, hmm, hmmm.\""},{"id":14047,"index":108,"key":"Talk_0118","CNzh":"<unk[3:0:0]><unk[4:0:12 87 97 107 101 117 112]>嗯……<unk[5:1]>有人来了达……？","TWzh":"<unk[3:0:0]><unk[4:0:12 87 97 107 101 117 112]>唔……<unk[5:1]>誰來了達……？","JPja":"<unk[3:0:0]><unk[4:0:12 87 97 107 101 117 112]>う～ん… <unk[5:1]>だれか<Ruby={2:2}き>来たのダ…？","USen":"<unk[3:0:0]><unk[4:0:12 87 97 107 101 117 112]>Mmm... <unk[5:1]>Is someone here?"},{"id":14048,"index":109,"key":"Talk_0097","CNzh":"<unk[3:0:7]>哦哦，是你啊。\n我一直在思考一件事。\n就是我能为微达做些什么……","TWzh":"<unk[3:0:7]>哦，是你啊。\n我一直在想，\n我到底能為微達做些什麼呢……","JPja":"<unk[3:0:7]>おぉ お<Ruby={2:4}まえ>前か<unk[5:0]>\nずっと <Ruby={2:6}かんが>考えていたんだ\nウィッダのために <Ruby={2:4}おれ>俺にできる<Ruby={2:4}こと>事を…","USen":"<unk[3:0:7]>Oh, it's you. <unk[5:1]>So, you know, I've been\ndoing a lot of thinking...\n\nTrying to figure out what I could possibly\ndo for Mattison."},{"id":14049,"index":110,"key":"Talk_0116","CNzh":"<unk[3:0:7]>答案就是，<unk[5:1]>这个。","TWzh":"<unk[3:0:7]>我想出的答案就是──<unk[5:1]>這個。","JPja":"<unk[3:0:7]>その<Ruby={2:4}こた>答えが <unk[5:1]>これだ","USen":"<unk[3:0:7]>And, well, <unk[5:1]>what I came up with is this."},{"id":14050,"index":111,"key":"Talk_0110","CNzh":"<unk[3:0:263]>格鲁德小镇离这里非常远，\n陆地上怪物也不少。\n所以，我打算做一个\n微达专用的特别气球！<unk[5:2]>","TWzh":"<unk[3:0:263]>畢竟格魯德小鎮離這裡很遙遠，\n這一路上地上的怪物也不少，\n所以我打算做一個\n微達專用的特別氣球！<unk[5:2]>","JPja":"<unk[3:0:263]>ゲルドの<Ruby={2:4}まち>街までは ここからかなり<Ruby={2:4}とお>遠いし\n<Ruby={4:8}ちじょう>地上には<Ruby={4:6}まもの>魔物も<Ruby={2:4}すく>少なくない\nだから ウィッダ<Ruby={4:8}せんよう>専用の<Ruby={4:8}とくべつ>特別な<Ruby={4:8}ききゅう>気球を\n<Ruby={2:4}つく>作ろうと<Ruby={2:4}おも>思ってるんだ！<unk[5:2]>","USen":"<unk[3:0:263]>Gerudo Town is pretty far from here,\nand there are plenty of monsters along\nthe way.\nSo, I thought I'd make Mattison her own\nspecial air balloon!"},{"id":14051,"index":112,"key":"Talk_0128","CNzh":"<unk[3:0:12]>……不过，怎么做才能让它”特别“呢……","TWzh":"<unk[3:0:12]>……但是，該怎麼做才能變得很特別呢……","JPja":"<unk[3:0:12]>…だが <Ruby={2:4}なに>何をすれば<Ruby={4:8}とくべつ>特別になるのか…","USen":"<unk[3:0:12]>But...I want to make it really special.\nSomething just for her. I'm just...not\nsure how to do that."},{"id":14052,"index":113,"key":"Talk_0114","CNzh":"<unk[3:0:8]><unk[4:0:22 71 114 101 101 116 105 110 103 95 48 49]>爸爸的气球像太阳公公一样，\n就算不是特别的，微达也喜欢！","TWzh":"<unk[3:0:8]><unk[4:0:22 71 114 101 101 116 105 110 103 95 48 49]>不特別也沒關係，\n爸爸做的氣球就像太陽公公一樣，微達很喜歡喔！","JPja":"<unk[3:0:8]><unk[4:0:22 71 114 101 101 116 105 110 103 95 48 49]><Ruby={4:8}とくべつ>特別じゃなくても パァパの<Ruby={4:8}ききゅう>気球<unk[5:0]>\nおひさまみたいで ウィッダ<Ruby={2:2}す>好きだよ！","USen":"<unk[3:0:8]><unk[4:0:22 71 114 101 101 116 105 110 103 95 48 49]>Special or not, I love the balloon you\nmade, Papa. It looks like the sun!"},{"id":14053,"index":114,"key":"Talk_0088","CNzh":"<unk[3:0:12]>太阳公公……<unk[5:1]>\n\n<unk[3:0:8]><unk[4:0:16 72 97 112 112 121 95 48 49]>有了！就像太阳一样，\n把它染成黄色吧！\n<unk[3:0:263]>之前在这附近看到有<Color=red>向阳草<Color=white>，\n如果拿它作染料，应该能染得很好。\n不过这么大的东西，需要<Color=red><unk[2:14:62 73 99 104 105 107 97 114 97 67 104 97 108 108 101 110 103 101 48 49 95 72 105 100 97 109 97 114 105 78 117 109 65535 52480]>个<Color=white>才行啊……","TWzh":"<unk[3:0:12]>太陽公公……<unk[5:1]>\n\n<unk[3:0:8]><unk[4:0:16 72 97 112 112 121 95 48 49]>對了，那就做得像太陽一樣，\n塗成黃色的吧。\n<unk[3:0:263]>如果使用附近見到過的<Color=red>向陽草<Color=white>做成染料，\n應該可以染出不錯的顏色。\n不過這個大小需要<Color=red><unk[2:14:62 73 99 104 105 107 97 114 97 67 104 97 108 108 101 110 103 101 48 49 95 72 105 100 97 109 97 114 105 78 117 109 65535 52480]>株<Color=white>吧……","JPja":"<unk[3:0:12]>おひさま…<unk[5:1]>\n\n<unk[3:0:8]><unk[4:0:16 72 97 112 112 121 95 48 49]>そうだ お<Ruby={4:6}ひさま>日様のように\n<Ruby={4:6}きいろ>黄色くカラーリングしよう\n<unk[3:0:263]><Ruby={2:4}まえ>前にこの<Ruby={2:4}あた>辺りで<Ruby={2:2}み>見かけた <Color=red>ヒダマリ<Ruby={2:4}そう>草<Color=white>を\n<Ruby={4:10}せんりょう>染料に<Ruby={2:4}つか>使えば <Ruby={2:2}い>良い<Ruby={4:6}いろあ>色合いが<Ruby={2:2}だ>出せそうだが\nこの<Ruby={2:4}おお>大きさだと <Color=red><unk[2:14:62 73 99 104 105 107 97 114 97 67 104 97 108 108 101 110 103 101 48 49 95 72 105 100 97 109 97 114 105 78 117 109 65535 52480]><Ruby={2:2}こ>個<Color=white>は<Ruby={4:8}ひつよう>必要だな…","USen":"<unk[3:0:12]>The sun...<unk[5:1]>\n\n\n<unk[3:0:8]><unk[4:0:16 72 97 112 112 121 95 48 49]>That's it! Let's color it yellow like\nthe sun.\n\n<unk[3:0:263]>I've seen <Color=red>sundelions<Color=white> around here. I could\nuse them to make a dye. Bet I'd get a\nbeautiful shade of yellow from them.\nBut for me to dye something this size,\nI'd need <Color=red><unk[2:14:62 73 99 104 105 107 97 114 97 67 104 97 108 108 101 110 103 101 48 49 95 72 105 100 97 109 97 114 105 78 117 109 65535 52480]> <Color=white>of them."},{"id":14054,"index":115,"key":"Talk_0089","CNzh":"<unk[3:0:8]><unk[4:0:30 84 97 108 107 80 111 115 105 116 105 118 101 95 48 49]>爸爸，你需要<Color=red>向阳草<Color=white>吗？\n是那种黄灿灿的花对吧？\n微达也要帮忙达！","TWzh":"<unk[3:0:8]><unk[4:0:30 84 97 108 107 80 111 115 105 116 105 118 101 95 48 49]>爸爸想要<Color=red>向陽草<Color=white>？\n就是指那個黃澄澄的花對吧？\n微達也來幫忙找達！","JPja":"<unk[3:0:8]><unk[4:0:30 84 97 108 107 80 111 115 105 116 105 118 101 95 48 49]>パァパ <Color=red>ヒダマリ<Ruby={2:4}そう>草<Color=white>がいるの？<unk[5:0]>\nあの まっきっきーなお<Ruby={2:4}はな>花でしょ？\nウィッダも お<Ruby={4:6}てつだ>手伝いするのダ！","USen":"<unk[3:0:8]><unk[4:0:30 84 97 108 107 80 111 115 105 116 105 118 101 95 48 49]>You need <Color=red>sundelions<Color=white>, Papa? Those are\nthe bright yellow flowers, right?\n\nI'll make finding them my new miss-son!"},{"id":14055,"index":116,"key":"Talk_0090","CNzh":"<unk[3:0:4]><unk[4:0:34 81 117 101 115 116 105 111 110 78 111 114 109 97 108 95 48 48]>我很开心，但你应该很难帮得上忙。\n向阳草是很珍稀的东西，\n我还不知道\n去哪里才能采到。","TWzh":"<unk[3:0:4]><unk[4:0:34 81 117 101 115 116 105 111 110 78 111 114 109 97 108 95 48 48]>你的心意爸爸很高興，但那對你來說太難了。\n向陽草是很稀有的東西，\n而且還不知道\n在哪裡可以採集得到。","JPja":"<unk[3:0:4]><unk[4:0:34 81 117 101 115 116 105 111 110 78 111 114 109 97 108 95 48 48]><Ruby={4:4}きも>気持ちはうれしいが さすがにきびしいだろう<unk[5:1]>\nヒダマリ<Ruby={2:4}そう>草は<Ruby={2:6}めずら>珍しいもので\nまだ どこで<Ruby={2:2}て>手に<Ruby={2:4}はい>入るのかも\nわかっていないんだ","USen":"<unk[3:0:4]><unk[4:0:34 81 117 101 115 116 105 111 110 78 111 114 109 97 108 95 48 48]>I appreciate the thought, but it's much too\ndifficult. Sundelions are quite rare.\n\nI'm not even sure where you'd find them."},{"id":14056,"index":117,"key":"Talk_0091","CNzh":"<unk[3:0:7]><unk[4:0:16 72 97 112 112 121 95 48 49]>没关系！微达见过向阳草嘛！\n从天上掉下来的遗迹上就嵌着一些达。","TWzh":"<unk[3:0:7]><unk[4:0:16 72 97 112 112 121 95 48 49]>沒問題！微達有看過向陽草！\n它就黏在從天上掉下來的遺跡上達。","JPja":"<unk[3:0:7]><unk[4:0:16 72 97 112 112 121 95 48 49]><Ruby={6:12}だいじょうぶ>大丈夫！<unk[5:0]> ヒダマリ<Ruby={2:4}そう>草<Ruby={2:2}み>見た<Ruby={2:4}こと>事あるモン！<unk[5:1]>\nお<Ruby={2:4}そら>空から<Ruby={2:2}お>落ちて<Ruby={2:2}き>来た<Ruby={4:6}いせき>遺跡に くっついてたのダ","USen":"<unk[3:0:7]><unk[4:0:16 72 97 112 112 121 95 48 49]>Don't worry! I've seen a sundelion before.\nIt was attached to the ruins that fell from\nthe sky."},{"id":14057,"index":118,"key":"Talk_0106","CNzh":"<unk[3:0:12]><unk[4:0:16 84 104 105 110 107 95 48 49]>天上啊……","TWzh":"<unk[3:0:12]><unk[4:0:16 84 104 105 110 107 95 48 49]>天上啊……","JPja":"<unk[3:0:12]><unk[4:0:16 84 104 105 110 107 95 48 49]><Ruby={2:4}そら>空か…","USen":"<unk[3:0:12]><unk[4:0:16 84 104 105 110 107 95 48 49]>The sky, huh?"},{"id":14058,"index":119,"key":"Near_0015","CNzh":"向阳草……","TWzh":"向陽草……","JPja":"ヒダマリ<Ruby={2:4}そう>草…","USen":"Sundelions...sundelions..."},{"id":14059,"index":120,"key":"Talk_1008","CNzh":"<unk[3:0:10]><unk[4:0:12 87 97 107 101 117 112]>微达已经很困了达……\n<Color=red>向阳草<Color=white>就明天再找达……","TWzh":"<unk[3:0:10]><unk[4:0:12 87 97 107 101 117 112]>微達已經好睏了達……\n明天再繼續找<Color=red>向陽草<Color=white>達……","JPja":"<unk[3:0:10]><unk[4:0:12 87 97 107 101 117 112]>ウィッダ さすがに<Ruby={2:4}ねむ>眠くなってきたのダ…<unk[5:1]>\n<Color=red>ヒダマリ<Ruby={2:4}そう>草<Color=white>は また<Ruby={6:10}あしたさが>明日探すのダ…","USen":"<unk[3:0:10]><unk[4:0:12 87 97 107 101 117 112]>I'm sooo tired. I'm not giving up\nmy miss-son. I'll look for <Color=red>sundelions<Color=white>\nagain tomorrow..."},{"id":14060,"index":121,"key":"Talk_1009","CNzh":"<unk[3:0:7]><unk[4:0:10 83 108 101 101 112]>微达要变成鸟……\n然后找到<Color=red>向阳草<Color=white>达……呼噜……","TWzh":"<unk[3:0:7]><unk[4:0:10 83 108 101 101 112]>微達想變成鳥兒……\n飛去找<Color=red>向陽草<Color=white>達……呼嚕。","JPja":"<unk[3:0:7]><unk[4:0:10 83 108 101 101 112]><Ruby={2:4}とり>鳥さんになって…<unk[5:1]>\n<Color=red>ヒダマリ<Ruby={2:4}そう>草<Color=white>を<Ruby={2:2}み>見つけるのダ… ムニャ","USen":"<unk[3:0:7]><unk[4:0:10 83 108 101 101 112]>I'll turn into a bird...fly through the air...\nfind the <Color=red>sundelions<Color=white>... *mumbling*"},{"id":14061,"index":122,"key":"Near_0012","CNzh":"要找向阳草了达！","TWzh":"要去找向陽草了達！","JPja":"ヒダマリ<Ruby={2:4}そう>草を<Ruby={2:4}さが>探すのダ！","USen":"Gotta find sundelions..."},{"id":14062,"index":123,"key":"Talk_0165","CNzh":"<unk[3:0:12]>是要找黄灿灿的<Color=red>向阳草<Color=white>啊。\n\n既然嵌在了从天上掉下来的遗迹上，\n那么<Color=red>天上<Color=white>是不是有花田呢……","TWzh":"<unk[3:0:12]>黃澄澄的<Color=red>向陽草<Color=white>啊……\n\n既然它黏在天上掉下來的遺跡上，\n那<Color=red>天上<Color=white>是不是有花園呢……","JPja":"<unk[3:0:12]>まっきっきーな <Color=red>ヒダマリ<Ruby={2:4}そう>草<Color=white>さんかぁ\n\nお<Ruby={2:4}そら>空から<Ruby={2:2}お>落ちて<Ruby={2:2}き>来た<Ruby={4:6}いせき>遺跡に ついてたってことは\n<Color=red>お<Ruby={2:4}そら>空<Color=white>に お<Ruby={4:10}はなばたけ>花畑があるのかなぁ…","USen":"<unk[3:0:12]>Hmmm...bright yellow <Color=red>sundelions<Color=white>...\n\n\nYou know, if it was attached to those\nruins that fell from up above, then maybe\nthere's a flower field in the <Color=red>sky<Color=white>."},{"id":14063,"index":124,"key":"Talk_0173","CNzh":"<unk[3:0:12]>这附近有没有呢……","TWzh":"<unk[3:0:12]>這附近有沒有長呢……？","JPja":"<unk[3:0:12]>どっかに<Ruby={2:2}は>生えてないかなぁ…","USen":"<unk[3:0:12]>I wonder if any of them are growing\nsomewhere..."},{"id":14064,"index":125,"key":"Talk_0153","CNzh":"<unk[3:0:7]>得快点完成才行……<unk[5:0]>\n万一微达淋雨生病就不好了。","TWzh":"<unk[3:0:7]>得快點完成才行……<unk[5:0]>\n要是這場雨害微達感冒就不好了。","JPja":"<unk[3:0:7]><Ruby={2:4}はや>早く<Ruby={4:8}かんせい>完成させなくては… <unk[5:0]>この<Ruby={2:4}あめ>雨で\nウィッダも<Ruby={4:10}たいちょう>体調を<Ruby={2:4}くず>崩したら<Ruby={4:8}たいへん>大変だ","USen":"<unk[3:0:7]>I need to finish this up quick. It'd be awful\nif Mattison got sick from being out in all\nthis rain."},{"id":14065,"index":126,"key":"Talk_0154","CNzh":"<unk[3:0:0]><unk[4:0:12 87 97 107 101 117 112]>嗯……微达闻到了太阳公公的味道达……","TWzh":"<unk[3:0:0]><unk[4:0:12 87 97 107 101 117 112]>唔嗯……有太陽公公的味道達……","JPja":"<unk[3:0:0]><unk[4:0:12 87 97 107 101 117 112]>う～ん… <unk[5:1]>おひさまのニオイがするのダ…","USen":"<unk[3:0:0]><unk[4:0:12 87 97 107 101 117 112]>Hm...I smell...the sun."},{"id":14066,"index":127,"key":"Talk_0152","CNzh":"<unk[3:0:12]>有<Color=red><unk[2:14:62 73 99 104 105 107 97 114 97 67 104 97 108 108 101 110 103 101 48 49 95 72 105 100 97 109 97 114 105 78 117 109 65535 52480]>个向阳草<Color=white>的话，\n应该就能染上鲜艳的黄色了。\n<unk[3:0:268]>可问题是，该怎么拿到呢……","TWzh":"<unk[3:0:12]>只要有<Color=red><unk[2:14:62 73 99 104 105 107 97 114 97 67 104 97 108 108 101 110 103 101 48 49 95 72 105 100 97 109 97 114 105 78 117 109 65535 52480]>株<Color=white>左右的<Color=red>向陽草<Color=white>，\n我就可以染出鮮豔的黃色了。\n<unk[3:0:268]>但問題是去哪收集呢……","JPja":"<unk[3:0:12]><Color=red>ヒダマリ<Ruby={2:4}そう>草<Color=white>が<Color=red><unk[2:14:62 73 99 104 105 107 97 114 97 67 104 97 108 108 101 110 103 101 48 49 95 72 105 100 97 109 97 114 105 78 117 109 65535 52480]><Ruby={2:2}こ>個<Color=white>もあれば\n<Ruby={2:4}あざ>鮮やかな<Ruby={4:6}きいろ>黄色に<Ruby={2:2}そ>染め<Ruby={2:2}あ>上げることができそうだが\n<unk[3:0:268]><Ruby={4:8}もんだい>問題は どうやって<Ruby={2:4}あつ>集めるか…","USen":"<unk[3:0:12]>If only I had <Color=red><unk[2:14:62 73 99 104 105 107 97 114 97 67 104 97 108 108 101 110 103 101 48 49 95 72 105 100 97 109 97 114 105 78 117 109 65535 52480]> sundelions<Color=white>, then I'd be\nable to dye the balloon a bright yellow.\n\n<unk[3:0:268]>But...I don't know where I'm going to\nget them from."},{"id":14067,"index":128,"key":"0008","CNzh":"给<unk[2:14:62 73 99 104 105 107 97 114 97 67 104 97 108 108 101 110 103 101 48 49 95 72 105 100 97 109 97 114 105 78 117 109 65535 52480]>个向阳草","TWzh":"給他<unk[2:14:62 73 99 104 105 107 97 114 97 67 104 97 108 108 101 110 103 101 48 49 95 72 105 100 97 109 97 114 105 78 117 109 65535 52480]>株向陽草","JPja":"ヒダマリ<Ruby={2:4}そう>草を<unk[2:14:62 73 99 104 105 107 97 114 97 67 104 97 108 108 101 110 103 101 48 49 95 72 105 100 97 109 97 114 105 78 117 109 65535 52480]><Ruby={4:6}こわた>個渡す","USen":"Here's <unk[2:14:62 73 99 104 105 107 97 114 97 67 104 97 108 108 101 110 103 101 48 49 95 72 105 100 97 109 97 114 105 78 117 109 65535 52480]> sundelions."},{"id":14068,"index":129,"key":"0009","CNzh":"不管他","TWzh":"不管他","JPja":"そっとしておく","USen":"I'll leave you to it."},{"id":14069,"index":130,"key":"Talk_0177","CNzh":"<unk[3:0:12]>微达说得没错，以前见过的<Color=red>向阳草<Color=white>\n确实都嵌在坠落遗迹上……\n说不定地面上\n并不会生长这种花……","TWzh":"<unk[3:0:12]>就如同微達所說的一樣，\n以前見過的<Color=red>向陽草<Color=white>也是長在墜落遺跡上……\n該不會地上\n沒有這種花吧……","JPja":"<unk[3:0:12]>ウィッダの<Ruby={2:2}い>言う<Ruby={2:4}とお>通り <unk[5:0]><Ruby={6:8}いぜんみ>以前見た<Color=red>ヒダマリ<Ruby={2:4}そう>草<Color=white>も\n<Ruby={2:4}たし>確かに<Ruby={8:12}らっかいせき>落下遺跡についていたな…\nもしかして <Ruby={4:8}ちじょう>地上には\n<Ruby={2:2}は>生えていないんじゃ…","USen":"<unk[3:0:12]>It's like Mattison said...the <Color=red>sundelion<Color=white>\nshe saw was attached to fallen ruins.\n\nSo it could be they don't grow down here\non the ground."},{"id":14070,"index":131,"key":"Talk_0167","CNzh":"<unk[3:0:11]><unk[4:0:24 83 117 114 112 114 105 115 101 76 95 48 49]><Size=125>达！？<Size=100><unk[5:2]><PageBreak><unk[3:0:8]>好厉害达！<unk[5:0]>\n真的凑齐了<unk[2:14:62 73 99 104 105 107 97 114 97 67 104 97 108 108 101 110 103 101 48 49 95 72 105 100 97 109 97 114 105 78 117 109 65535 52480]>个达！","TWzh":"<unk[3:0:11]><unk[4:0:24 83 117 114 112 114 105 115 101 76 95 48 49]><Size=125>達！？<Size=100><unk[5:2]><PageBreak><unk[3:0:8]>好厲害達！\n居然收齊<unk[2:14:62 73 99 104 105 107 97 114 97 67 104 97 108 108 101 110 103 101 48 49 95 72 105 100 97 109 97 114 105 78 117 109 65535 52480]>株了達！","JPja":"<unk[3:0:11]><unk[4:0:24 83 117 114 112 114 105 115 101 76 95 48 49]><Size=125>のダッ！？<Size=100><unk[5:2]><PageBreak><unk[3:0:8]>すごいのダ！<unk[5:0]>\nちゃんと<unk[2:14:62 73 99 104 105 107 97 114 97 67 104 97 108 108 101 110 103 101 48 49 95 72 105 100 97 109 97 114 105 78 117 109 65535 52480]><Ruby={2:2}こ>個 <Ruby={2:4}そろ>揃ってるのダ！","USen":"<unk[3:0:11]><unk[4:0:24 83 117 114 112 114 105 115 101 76 95 48 49]><Size=125>Huh?!<Size=100><unk[5:1]><PageBreak><unk[3:0:8]>That's awesome! <unk[5:0]>You did it! You really\nand truly collected <unk[2:14:62 73 99 104 105 107 97 114 97 67 104 97 108 108 101 110 103 101 48 49 95 72 105 100 97 109 97 114 105 78 117 109 65535 52480]> of them!"},{"id":14071,"index":132,"key":"Talk_0183","CNzh":"<unk[3:0:8]><unk[4:0:16 72 97 112 112 121 95 48 48]>天啊……你为我们收集了这些？\n有这么多的话，就能把气球染成太阳的颜色了。","TWzh":"<unk[3:0:8]><unk[4:0:16 72 97 112 112 121 95 48 48]>這是……你居然幫我們收集來了啊。\n只要有了這些，氣球就能染成太陽公公的顏色了。","JPja":"<unk[3:0:8]><unk[4:0:16 72 97 112 112 121 95 48 48]>なんと… <Ruby={2:4}あつ>集めてきてくれたのか<unk[5:0]>\nそれだけあれば <Ruby={4:8}ききゅう>気球をお<Ruby={6:10}ひさまいろ>日様色に<Ruby={2:2}そ>染められるぞ","USen":"<unk[3:0:8]><unk[4:0:16 72 97 112 112 121 95 48 48]>What's this? You found them all for us?\nLooks like I'll have no problem dyeing the\nballoon the color of the sun."},{"id":14072,"index":133,"key":"Talk_0184","CNzh":"<unk[3:0:10]>对不起达……\n微达什么忙都没帮上达……","TWzh":"<unk[3:0:10]>抱歉達……\n微達什麼忙都沒幫上達……","JPja":"<unk[3:0:10]>ごめんなのダ…<unk[5:0]>\nウィッダ <Ruby={2:4}なに>何もお<Ruby={4:6}てつだ>手伝いできなかったのダ…","USen":"<unk[3:0:10]>Awww, I wasn't any help at all. I failed\nmy miss-son."},{"id":14073,"index":134,"key":"Talk_0185","CNzh":"<unk[3:0:7]><unk[4:0:16 72 97 112 112 121 95 48 49]>不，别这么说，微达。<PageBreak>爸爸接下来要去把气球\n做成太阳公公，\n你能来帮忙吗？","TWzh":"<unk[3:0:7]><unk[4:0:16 72 97 112 112 121 95 48 49]>怎麼會呢，微達。<PageBreak>爸爸接下來要去\n把這顆氣球變成太陽公公了，\n你可以來幫爸爸嗎？","JPja":"<unk[3:0:7]><unk[4:0:16 72 97 112 112 121 95 48 49]>いいや そんなことはないぞ ウィッダ<PageBreak>これから パァパは\nこの<Ruby={4:8}ききゅう>気球を お<Ruby={4:6}ひさま>日様にするんだ\n<Ruby={4:6}てつだ>手伝ってくれるか？","USen":"<unk[3:0:7]><unk[4:0:16 72 97 112 112 121 95 48 49]>That's not true, Mattison.<PageBreak>Your papa is about to turn this balloon\ninto the sun, isn't he?\n\nI know, why don't you help me with that?"},{"id":14074,"index":135,"key":"Talk_0187","CNzh":"<unk[3:0:8]>嗯！\n微达也要帮忙做太阳公公达！","TWzh":"<unk[3:0:8]>嗯！\n微達也要做太陽公公達！","JPja":"<unk[3:0:8]>うんっ！<unk[5:1]>\nウィッダも おひさま<Ruby={2:4}つく>作るのダ！","USen":"<unk[3:0:8]>I will! I will, Papa! I'll help you make\nthe sun!"},{"id":14075,"index":136,"key":"Talk_0194","CNzh":"<unk[4:0:14 72 117 109 109 105 110 103]>哒哒一下决定♪哒哒一下建造～♪","TWzh":"<unk[4:0:14 72 117 109 109 105 110 103]>噠噠地建造～♪噠噠地搞定～♪","JPja":"<unk[4:0:14 72 117 109 109 105 110 103]>ダダっと<Ruby={2:2}き>決めて♪ <unk[5:0]>ダダっと<Ruby={2:4}つく>作る～♪","USen":"<unk[4:0:14 72 117 109 109 105 110 103]>♪Quick and quality, blink and\nwe're done!♪"},{"id":14076,"index":137,"key":"Talk_0201","CNzh":"<unk[4:0:14 72 117 109 109 105 110 103]>DADADA～当你需要就来找，\n松达建筑～店～♪","TWzh":"<unk[4:0:14 72 117 109 109 105 110 103]>DADADA，任誰都一定要來一次\n松達～建築店～♪","JPja":"<unk[4:0:14 72 117 109 109 105 110 103]>DADADA <Ruby={2:4}だれ>誰でも<Ruby={4:6}いちど>一度は<unk[5:0]>\nエノキダこうむて～ん～♪","USen":"<unk[4:0:14 72 117 109 109 105 110 103]>♪That's why every-son chooses Hudson\nConstruct-sooon!♪"},{"id":14077,"index":138,"key":"Talk_0188","CNzh":"<unk[3:0:7]>……好，完成了。<unk[5:0]>\n一下就干到了早上啊。","TWzh":"<unk[3:0:7]>……好，完成了。\n已經完全天亮了呢。","JPja":"<unk[3:0:7]>…よし <Ruby={4:8}かんせい>完成だ<unk[5:0]>\nすっかり<Ruby={2:4}あさ>朝になってしまったな","USen":"<unk[3:0:7]>At last. It's done. And morning is\nalready here."},{"id":14078,"index":139,"key":"Talk_0206","CNzh":"<unk[3:0:7]>……好，完成了。<unk[5:0]>\n已经早上了啊……看来是干了一整天。","TWzh":"<unk[3:0:7]>好……完成！<unk[5:0]>\n已經早上啦……花了整整一天呢。","JPja":"<unk[3:0:7]>…よし <Ruby={4:8}かんせい>完成だ<unk[5:0]>\nもう<Ruby={2:4}あさ>朝か… <Ruby={6:12}まるいちにち>丸一日かかってしまったな","USen":"<unk[3:0:7]>OK. It's done. <unk[5:0]>It's already morning, eh?\nGuess that took a whole day."},{"id":14079,"index":140,"key":"Talk_0189","CNzh":"<unk[3:0:263]>……还有点时间，\n能让我看看孩子的睡脸。","TWzh":"<unk[3:0:263]>……能這樣看著孩子睡臉的時間\n也只剩一點點了啊。","JPja":"<unk[3:0:263]>…<Ruby={2:2}わ>我が<Ruby={2:2}こ>子の<Ruby={4:6}ねがお>寝顔が<Ruby={2:2}み>見られるのも\nもう<Ruby={2:4}すこ>少しなんだなぁ","USen":"<unk[3:0:263]>I'm just happy I get to watch my little one\nsleep a bit longer."},{"id":14080,"index":141,"key":"Talk_0190","CNzh":"<unk[3:0:260]><unk[4:0:28 85 110 99 111 110 115 99 105 111 117 115 95 48 48]>松达！","TWzh":"<unk[3:0:260]><unk[4:0:28 85 110 99 111 110 115 99 105 111 117 115 95 48 48]>松達！","JPja":"<unk[3:0:260]><unk[4:0:28 85 110 99 111 110 115 99 105 111 117 115 95 48 48]>エノキダ！","USen":"<unk[3:0:260]><unk[4:0:28 85 110 99 111 110 115 99 105 111 117 115 95 48 48]>Hudson!"},{"id":14081,"index":142,"key":"Talk_0191","CNzh":"<unk[3:0:7]><unk[4:0:18 78 111 116 105 99 101 95 48 49]>帕伍达啊……\n怎么这么慌张……<unk[5:2]>难道是——","TWzh":"<unk[3:0:7]><unk[4:0:18 78 111 116 105 99 101 95 48 49]>是帕伍達啊……\n你怎麼這麼慌張……<unk[5:2]>難道說！？","JPja":"<unk[3:0:7]><unk[4:0:18 78 111 116 105 99 101 95 48 49]>パウダか…<unk[5:0]>\nどうしたんだ そんなに<Ruby={2:4}あわ>慌てて… <unk[5:1]>まさか","USen":"<unk[3:0:7]><unk[4:0:18 78 111 116 105 99 101 95 48 49]>Oh, Rhondson! What's wrong?<unk[5:1]> No, don't\ntell me—"},{"id":14082,"index":143,"key":"Talk_0192","CNzh":"<unk[3:0:7]><unk[4:0:14 69 97 115 101 95 48 48]>嗯……接她的人来了，\n说是在村子入口处等着。","TWzh":"<unk[3:0:7]><unk[4:0:14 69 97 115 101 95 48 48]>對，迎接的人來了……\n說是在村子入口等待。","JPja":"<unk[3:0:7]><unk[4:0:14 69 97 115 101 95 48 48]>えぇ… <unk[5:0]><Ruby={2:4}むか>迎えが<Ruby={2:2}き>来たわ<unk[5:1]>\n<Ruby={2:4}むら>村の<Ruby={2:2}い>入り<Ruby={2:4}ぐち>口で<Ruby={2:2}ま>待ってるって","USen":"<unk[3:0:7]><unk[4:0:14 69 97 115 101 95 48 48]>Yes. Her escort has arrived and is waiting\nat the village entrance."},{"id":14083,"index":144,"key":"Talk_0195","CNzh":"<unk[3:0:7]><unk[4:0:12 83 97 100 95 48 48]>是吗……<unk[5:2]>那好。","TWzh":"<unk[3:0:7]><unk[4:0:12 83 97 100 95 48 48]>這樣啊……<unk[5:2]>好！","JPja":"<unk[3:0:7]><unk[4:0:12 83 97 100 95 48 48]>そうか… <unk[5:2]>よし","USen":"<unk[3:0:7]><unk[4:0:12 83 97 100 95 48 48]>I see. <unk[5:1]>All right."},{"id":14084,"index":145,"key":"Talk_0193","CNzh":"<unk[3:0:7]>我们一起去吧，\n坐上微达专用的太阳公公气球！","TWzh":"<unk[3:0:7]>那我們一起去吧！\n搭上微達專用的太陽公公氣球！","JPja":"<unk[3:0:7]>じゃあ <Ruby={2:4}みな>皆で<Ruby={2:2}い>行こうか<unk[5:1]>\nウィッダ<Ruby={4:8}せんよう>専用お<Ruby={4:6}ひさま>日様<Ruby={4:8}ききゅう>気球に<Ruby={2:2}の>乗って！","USen":"<unk[3:0:7]>Let's all go together, then. In Mattison's\nspecial sun balloon!"},{"id":14085,"index":146,"key":"Talk_0205","CNzh":"<unk[3:0:0]>你要不要<unk[5:0]>也一起去？","TWzh":"<unk[3:0:0]>你也要<unk[5:0]>一起來嗎？","JPja":"<unk[3:0:0]>お<Ruby={2:4}まえ>前も <unk[5:0]><Ruby={4:8}いっしょ>一緒に<Ruby={2:2}き>来てくれるか","USen":"<unk[3:0:0]>Would you <unk[5:0]>join us as well?"},{"id":14086,"index":147,"key":"Talk_0159","CNzh":"<unk[3:0:8]><unk[4:0:16 72 97 112 112 121 95 48 49]>好厉害达！\n微达现在像鸟儿一样达！","TWzh":"<unk[3:0:8]><unk[4:0:16 72 97 112 112 121 95 48 49]>好厲害達！\n微達變得像鳥兒一樣了達！","JPja":"<unk[3:0:8]><unk[4:0:16 72 97 112 112 121 95 48 49]>すごいのダ！<unk[5:1]>\nウィッダ <Ruby={2:4}とり>鳥さんになってるのダ！","USen":"<unk[3:0:8]><unk[4:0:16 72 97 112 112 121 95 48 49]>Wooow! I feel like I've turned into a bird!"},{"id":14087,"index":148,"key":"Talk_0171","CNzh":"<unk[3:0:7]><unk[4:0:18 76 97 117 103 104 83 95 48 49]>别太乱来哦，微达，\n要是掉下去就糟了。","TWzh":"<unk[3:0:7]><unk[4:0:18 76 97 117 103 104 83 95 48 49]>微達，不可以太激動喔。\n要是掉下去可就危險了。","JPja":"<unk[3:0:7]><unk[4:0:18 76 97 117 103 104 83 95 48 49]>あまり<Ruby={2:4}さわ>騒いじゃダメよ ウィッダ<unk[5:1]>\n<Ruby={2:2}お>落ちたら<Ruby={2:4}あぶ>危ないわ","USen":"<unk[3:0:7]><unk[4:0:18 76 97 117 103 104 83 95 48 49]>Oh, Mattison, don't make such a ruckus.\nYou do not want to fall from this height."},{"id":14088,"index":149,"key":"Talk_0162","CNzh":"<unk[3:0:263]><unk[4:0:30 84 97 108 107 80 111 115 105 116 105 118 101 95 48 49]>……各位，快看。","TWzh":"<unk[3:0:263]><unk[4:0:30 84 97 108 107 80 111 115 105 116 105 118 101 95 48 49]>……各位，看那邊。","JPja":"<unk[3:0:263]><unk[4:0:30 84 97 108 107 80 111 115 105 116 105 118 101 95 48 49]>…みんな <Ruby={2:2}み>見てみろ","USen":"<unk[3:0:263]><unk[4:0:30 84 97 108 107 80 111 115 105 116 105 118 101 95 48 49]>Hey, everyone. Take a look at that."},{"id":14089,"index":150,"key":"Talk_0168","CNzh":"<unk[3:0:1]><unk[4:0:16 72 97 112 112 121 95 48 48]>是太阳公公！\n太阳公公也起床了达！","TWzh":"<unk[3:0:1]><unk[4:0:16 72 97 112 112 121 95 48 48]>是太陽公公！\n太陽公公也起床了達！","JPja":"<unk[3:0:1]><unk[4:0:16 72 97 112 112 121 95 48 48]>おひさまだ！<unk[5:0]>\nおひさまも <Ruby={2:2}お>起きてきたのダ！","USen":"<unk[3:0:1]><unk[4:0:16 72 97 112 112 121 95 48 48]>The sun is waking up!"},{"id":14090,"index":151,"key":"Talk_0169","CNzh":"<unk[3:0:0]><unk[4:0:30 84 97 108 107 80 111 115 105 116 105 118 101 95 48 48]>太阳也在祝福微达\n一路顺利呢。","TWzh":"<unk[3:0:0]><unk[4:0:30 84 97 108 107 80 111 115 105 116 105 118 101 95 48 48]>太陽也在祝福微達\n踏上旅程呢。","JPja":"<unk[3:0:0]><unk[4:0:30 84 97 108 107 80 111 115 105 116 105 118 101 95 48 48]><Ruby={4:8}たいよう>太陽も ウィッダの<Ruby={4:6}かどで>門出を\n<Ruby={4:10}しゅくふく>祝福してくれているのね","USen":"<unk[3:0:0]><unk[4:0:30 84 97 108 107 80 111 115 105 116 105 118 101 95 48 48]>It's blessing the start of your\njourney, Mattison."},{"id":14091,"index":152,"key":"Talk_0104","CNzh":"<unk[3:0:263]>不管你在格鲁德小镇还是一始村，\n我们抬头看见的都是同一个太阳。","TWzh":"<unk[3:0:263]>不論在格魯德小鎮或是在一始村，\n我們看見的都是同一個太陽喔。","JPja":"<unk[3:0:263]>ゲルドの<Ruby={2:4}まち>街にいても イチカラ<Ruby={2:4}むら>村にいても<unk[5:0]>\n<Ruby={2:6}わたし>私たちが<Ruby={2:2}み>見ている<Ruby={4:8}たいよう>太陽は<Ruby={2:4}おな>同じよ","USen":"<unk[3:0:263]>Whether you're in Gerudo Town or Tarrey\nTown, never forget that we are all\nstanding beneath the very same sun."},{"id":14092,"index":153,"key":"Talk_0107","CNzh":"<unk[3:0:1]><unk[4:0:18 76 97 117 103 104 83 95 48 48]>重要的是心与心的距离，<unk[5:0]>\n所以妈妈永远都在你的身边。","TWzh":"<unk[3:0:1]><unk[4:0:18 76 97 117 103 104 83 95 48 48]>最重要的是心與心之間的距離，<unk[5:0]>\n媽媽永遠都陪伴在你身邊喔。","JPja":"<unk[3:0:1]><unk[4:0:18 76 97 117 103 104 83 95 48 48]><Ruby={4:6}だいじ>大事なのは<Ruby={2:6}こころ>心の<Ruby={4:6}きょり>距離<unk[5:0]>\nマァマは いつでもあなたの<Ruby={2:4}そば>側にいるからね","USen":"<unk[3:0:1]><unk[4:0:18 76 97 117 103 104 83 95 48 48]>The only distance that matters is the\ndistance between our hearts.<unk[5:0]> So you see,\nyour mama will always be beside you."},{"id":14093,"index":154,"key":"Talk_0170","CNzh":"<unk[3:0:256]><unk[4:0:30 84 97 108 107 80 111 115 105 116 105 118 101 95 48 48]>……好了，差不多该着陆了。\n抓紧了哦。","TWzh":"<unk[3:0:256]><unk[4:0:30 84 97 108 107 80 111 115 105 116 105 118 101 95 48 48]>……好了，差不多要著地了。\n要好好地抓穩喔。","JPja":"<unk[3:0:256]><unk[4:0:30 84 97 108 107 80 111 115 105 116 105 118 101 95 48 48]>…さぁ そろそろ<Ruby={4:10}ちゃくりく>着陸だ<unk[5:1]>\nしっかり つかまっているんだぞ","USen":"<unk[3:0:256]><unk[4:0:30 84 97 108 107 80 111 115 105 116 105 118 101 95 48 48]>We'll be touching down soon. Hold\non tight."},{"id":14094,"index":155,"key":"Talk_0102","CNzh":"<unk[3:0:8]>爸爸的礼物真棒，\n微达好开心达！","TWzh":"<unk[3:0:8]>爸爸給的禮物\n讓微達非常開心達！","JPja":"<unk[3:0:8]>パァパからのプレゼント\nすっごくうれしかったのダ！","USen":"<unk[3:0:8]>Papa, your present made me very happy!"},{"id":14095,"index":156,"key":"Talk_0105","CNzh":"<unk[3:0:10]>……<unk[5:1]>微达，<unk[5:0]>\n要是觉得孤单，随时回……<unk[5:1]>","TWzh":"<unk[3:0:10]>……<unk[5:1]>微達，<unk[5:0]>\n如果你感到寂寞隨時可以回……<unk[5:1]>","JPja":"<unk[3:0:10]>…ウィッダ<unk[5:1]>\n<Ruby={2:4}さみ>寂しくなったら いつでも<Ruby={2:4}もど>戻…<unk[5:1]>","USen":"<unk[3:0:10]>Mattison...<unk[5:1]>you know...<unk[5:0]>if you get lonely,\nyou can come back any—<unk[5:1]>"},{"id":14096,"index":157,"key":"Talk_0109","CNzh":"<unk[3:0:1]>不……<unk[5:0]>没什么。<unk[5:1]>\n爸爸也得像微达一样坚强才行。\n我们可爱的微达，<unk[5:1]>\n去吧，出发吧。","TWzh":"<unk[3:0:1]>不……<unk[5:0]>沒什麼。<unk[5:1]>\n爸爸也得變得和微達一樣堅強才行呢。\n好了，我們可愛的微達，<unk[5:1]>\n路上小心。","JPja":"<unk[3:0:1]>いや… <unk[5:0]>なんでもない<unk[5:1]>\nパァパもウィッダみたいに<Ruby={2:4}つよ>強くならないとな\n<Ruby={4:8}おれたち>俺達のかわいいウィッダ<unk[5:1]>\nさあ <Ruby={2:2}い>行っておいで","USen":"<unk[3:0:1]>Sorry...<unk[5:0]>never mind.<unk[5:1]> Papa needs to be\nstrong just like you.\n\nMy little Mattison...<unk[5:1]>it's time for you to go\non your big adventure."},{"id":14097,"index":158,"key":"Talk_0156","CNzh":"<unk[3:0:263]><unk[4:0:12 83 97 100 95 48 48]>……我知道的，<unk[5:1]>到时间了。","TWzh":"<unk[3:0:263]><unk[4:0:12 83 97 100 95 48 48]>……我知道，<unk[5:1]>時間到了吧。","JPja":"<unk[3:0:263]><unk[4:0:12 83 97 100 95 48 48]>…わかっているよ<unk[5:1]> <Ruby={4:6}じかん>時間だな","USen":"<unk[3:0:263]><unk[4:0:12 83 97 100 95 48 48]>Yes...<unk[5:1]> It's time."},{"id":14098,"index":159,"key":"Talk_0198","CNzh":"<unk[3:0:0]><unk[4:0:30 84 97 108 107 80 111 115 105 116 105 118 101 95 48 49]>我会照顾好你爸爸妈妈的，\n放心去吧。","TWzh":"<unk[3:0:0]><unk[4:0:30 84 97 108 107 80 111 115 105 116 105 118 101 95 48 49]>奶奶會照顧你爸爸媽媽的，\n你就放心去吧。","JPja":"<unk[3:0:0]><unk[4:0:30 84 97 108 107 80 111 115 105 116 105 118 101 95 48 49]>パァパとマァマのお<Ruby={4:4}せわ>世話は\n<Ruby={2:6}わたし>私に<Ruby={2:4}まか>任せて <Ruby={4:8}あんしん>安心していってらっしゃいねぇ","USen":"<unk[3:0:0]><unk[4:0:30 84 97 108 107 80 111 115 105 116 105 118 101 95 48 49]>You can trust me. I'll take care of your\npapa and mama. Don't worry, you can go."},{"id":14099,"index":160,"key":"Talk_0204","CNzh":"<unk[3:0:1]><unk[4:0:18 76 97 117 103 104 83 95 48 49]>去成为优秀的芭伊，\n回来再给我讲各种各样的故事吧。\n我很期待。","TWzh":"<unk[3:0:1]><unk[4:0:18 76 97 117 103 104 83 95 48 49]>奶奶很期待你回來時\n變成一個漂亮的芭伊，\n說各種故事給我聽喔。","JPja":"<unk[3:0:1]><unk[4:0:18 76 97 117 103 104 83 95 48 49]>ステキなヴァーイになって\nまた<Ruby={4:8}いろいろ>色々お<Ruby={4:8}はなしき>話聞かせてもらえるのを\n<Ruby={2:4}たの>楽しみに<Ruby={2:2}ま>待っていますからねぇ","USen":"<unk[3:0:1]><unk[4:0:18 76 97 117 103 104 83 95 48 49]>Go become a wonderful vai, and come\nback with lots of stories to tell.\n\nI can't wait to hear about your\nadventures!"},{"id":14100,"index":161,"key":"Talk_0199","CNzh":"<unk[3:0:8]><unk[4:0:16 72 97 112 112 121 95 48 49]>我会找时间去格鲁德小镇的！\n到时候我们再一起玩吧！","TWzh":"<unk[3:0:8]><unk[4:0:16 72 97 112 112 121 95 48 49]>我總有一天會去格魯德小鎮玩的！\n到時候我們再一起玩吧！","JPja":"<unk[3:0:8]><unk[4:0:16 72 97 112 112 121 95 48 49]>いつかゲルドの<Ruby={2:4}まち>街に<Ruby={2:4}あそ>遊びに<Ruby={2:2}い>行くね！<unk[5:1]>\nそしたらまた<Ruby={2:4}あそ>遊ぼうね！","USen":"<unk[3:0:8]><unk[4:0:16 72 97 112 112 121 95 48 49]>I'll come visit you in Gerudo Town\nsometime. When I do, let's play again!"},{"id":14101,"index":162,"key":"Talk_0147","CNzh":"<unk[3:0:8]><unk[4:0:18 76 97 117 103 104 76 95 48 49]>谢谢你们……\n……不，是萨库萨库达！","TWzh":"<unk[3:0:8]><unk[4:0:18 76 97 117 103 104 76 95 48 49]>大家，謝謝你們……\n不對，是薩庫薩庫達！","JPja":"<unk[3:0:8]><unk[4:0:18 76 97 117 103 104 76 95 48 49]>みんな ありがと…<unk[5:1]>\n…いや サークサークなのダ！","USen":"<unk[3:0:8]><unk[4:0:18 76 97 117 103 104 76 95 48 49]>Thank you, every-son. I mean...sarqso!"},{"id":14102,"index":163,"key":"Talk_0148","CNzh":"<unk[3:0:1]><unk[4:0:30 84 97 108 107 80 111 115 105 116 105 118 101 95 48 48]>微达要成为\n像妈妈一样的好芭伊，\n再找到一个\n像爸爸一样的帅伯伊达！","TWzh":"<unk[3:0:1]><unk[4:0:30 84 97 108 107 80 111 115 105 116 105 118 101 95 48 48]>微達會變成一個\n像媽媽一樣漂亮的芭伊，\n然後找到一個\n像爸爸一樣帥氣的伯伊達！","JPja":"<unk[3:0:1]><unk[4:0:30 84 97 108 107 80 111 115 105 116 105 118 101 95 48 48]>ウィッダは マァマみたいに\nステキなヴァーイになって\nパァパみたいな\nカッコいいヴォーイを<Ruby={2:4}さが>探すのダ！","USen":"<unk[3:0:1]><unk[4:0:30 84 97 108 107 80 111 115 105 116 105 118 101 95 48 48]>I'm going to become a great vai\nlike Mama.\n\nAnd I'll meet a wonderful voe like Papa!"},{"id":14103,"index":164,"key":"Talk_0158","CNzh":"<Size=125><unk[3:0:8]><unk[4:0:22 71 114 101 101 116 105 110 103 95 48 48]>大家，萨伯库达！<Size=100>","TWzh":"<Size=125><unk[3:0:8]><unk[4:0:22 71 114 101 101 116 105 110 103 95 48 48]>大家，薩伯庫達！<Size=100>","JPja":"<Size=125><unk[3:0:8]><unk[4:0:22 71 114 101 101 116 105 110 103 95 48 48]>みんな サヴォークなのダ！<Size=100>","USen":"<Size=125><unk[3:0:8]><unk[4:0:22 71 114 101 101 116 105 110 103 95 48 48]>Sav'orq, every-son!<Size=100>"},{"id":14104,"index":165,"key":"Talk_0141","CNzh":"<unk[3:0:3]><unk[4:0:12 83 97 100 95 48 48]>帕伍达……我保持住笑脸了吗……","TWzh":"<unk[3:0:3]><unk[4:0:12 83 97 100 95 48 48]>帕伍達……我有好好面帶笑容到最後嗎……","JPja":"<unk[3:0:3]><unk[4:0:12 83 97 100 95 48 48]>パウダよ… <unk[5:1]><Ruby={2:4}おれ>俺は<Ruby={4:6}えがお>笑顔を<Ruby={2:4}たも>保てていただろうか…","USen":"<unk[3:0:3]><unk[4:0:12 83 97 100 95 48 48]>Rhondson...did I manage to keep a smile\non my face?"},{"id":14105,"index":166,"key":"Talk_0139","CNzh":"<unk[3:0:7]><unk[4:0:12 83 97 100 95 48 48]>嗯，你很努力了。\n\n那孩子都没有掉眼泪，\n我们又有什么道理哭呢……<unk[5:2]>","TWzh":"<unk[3:0:7]><unk[4:0:12 83 97 100 95 48 48]>是啊，你做到了呢。\n\n那孩子都沒有哭了，\n我們怎麼能在他面前哭出來呢……<unk[5:2]>","JPja":"<unk[3:0:7]><unk[4:0:12 83 97 100 95 48 48]>ええ <unk[5:0]><Ruby={4:6}がんば>頑張ったわね\n\nあの<Ruby={2:2}こ>子が<Ruby={2:6}なみだ>涙を<Ruby={2:2}み>見せないのに\n<Ruby={4:10}わたしたち>私達が<Ruby={2:2}な>泣くわけには いかないものね…<unk[5:2]>","USen":"<unk[3:0:7]><unk[4:0:12 83 97 100 95 48 48]>Yes. You did great.\n\n\nShe didn't cry, so it's good we didn't\ncry either."},{"id":14106,"index":167,"key":"Talk_0142","CNzh":"<unk[3:0:263]>好了，<unk[5:0]>接下来\n我们也要开始新生活了。\n<unk[4:0:22 71 114 101 101 116 105 110 103 95 48 48]>我们来……<unk[5:0]>重整旗鼓吧！","TWzh":"<unk[3:0:263]>好了，<unk[5:0]>從現在起\n我們也得開始過新生活了，\n<unk[4:0:22 71 114 101 101 116 105 110 103 95 48 48]>要重新打起精神……<unk[5:1]>你說是吧！","JPja":"<unk[3:0:263]>さあ <unk[5:0]><Ruby={4:10}わたしたち>私達にとっても\n<Ruby={2:6}あたら>新しい<Ruby={4:8}せいかつ>生活のスタートなんだから\n<unk[4:0:22 71 114 101 101 116 105 110 103 95 48 48]><Ruby={2:2}き>気を<Ruby={2:2}と>取り<Ruby={2:4}なお>直して… <unk[5:1]>ね！","USen":"<unk[3:0:263]>Now,<unk[5:0]> this is the start of a new life for\nus too.\n\n<unk[4:0:22 71 114 101 101 116 105 110 103 95 48 48]>Let's pull ourselves together...<unk[5:1]>if\nyou're ready?"},{"id":14107,"index":168,"key":"Talk_0140","CNzh":"<unk[3:0:7]><unk[4:0:12 83 97 100 95 48 49]>嗯……<unk[5:2]>你说得对……<unk[5:2]>\n……<unk[5:1]>……<unk[5:1]>……<unk[5:1]>好。","TWzh":"<unk[3:0:7]><unk[4:0:12 83 97 100 95 48 49]>啊……<unk[5:0]>說得也是……<unk[5:2]>\n……<unk[5:1]>好。","JPja":"<unk[3:0:7]><unk[4:0:12 83 97 100 95 48 49]>あぁ… <unk[5:0]>そうだな…<unk[5:2]>\n…<unk[5:1]> … <unk[5:1]>…ヨシ ","USen":"<unk[3:0:7]><unk[4:0:12 83 97 100 95 48 49]>Yes. <unk[5:1]>You're right, of course...<unk[5:1]> Ahem...<unk[5:1]>\nOK, I am...<unk[5:1]>ready."},{"id":14108,"index":169,"key":"Talk_0161","CNzh":"<unk[3:0:7]><unk[4:0:30 84 97 108 107 80 111 115 105 116 105 118 101 95 48 48]>啊，不好意思。\n你也帮了不少忙啊，<unk[5:1]>谢谢了。\n那个向阳草应该很贵重吧？\n我准备了这个以表谢意，请收下吧。","TWzh":"<unk[3:0:7]><unk[4:0:30 84 97 108 107 80 111 115 105 116 105 118 101 95 48 48]>啊，真不好意思。\n給你添麻煩了呢，<unk[5:1]>謝謝你。\n那個向陽草應該很貴重吧？\n這是我的一點心意，請收下吧。","JPja":"<unk[3:0:7]><unk[4:0:30 84 97 108 107 80 111 115 105 116 105 118 101 95 48 48]>ああ すまんな<unk[5:0]>\nお<Ruby={2:4}まえ>前にも<Ruby={4:4}せわ>世話になったな<unk[5:1]> ありがとう\nあのヒダマリ<Ruby={2:4}そう>草は <Ruby={4:8}きちょう>貴重なものだったんだろう？<unk[5:1]>\n<Ruby={4:8}かんしゃ>感謝の<Ruby={4:4}きも>気持ちだ<unk[5:0]> <Ruby={2:2}う>受け<Ruby={2:2}と>取ってくれ","USen":"<unk[3:0:7]><unk[4:0:30 84 97 108 107 80 111 115 105 116 105 118 101 95 48 48]>Ah, sorry about that.<unk[5:1]> You know, you really\nwere a big help to me. Honestly, I can't\nthank you enough.\nThose sundelions were pretty valuable,\nweren't they? Well, as a way of saying\nthank you...please, take this."},{"id":14109,"index":170,"key":"Talk_0186","CNzh":"<unk[3:0:7]><unk[4:0:30 84 97 108 107 80 111 115 105 116 105 118 101 95 48 48]>我也有谢礼要给你……","TWzh":"<unk[3:0:7]><unk[4:0:30 84 97 108 107 80 111 115 105 116 105 118 101 95 48 48]>還有我這邊也……","JPja":"<unk[3:0:7]><unk[4:0:30 84 97 108 107 80 111 115 105 116 105 118 101 95 48 48]><Ruby={2:6}わたし>私からも…","USen":"<unk[3:0:7]><unk[4:0:30 84 97 108 107 80 111 115 105 116 105 118 101 95 48 48]>And this is from me..."},{"id":14110,"index":171,"key":"Talk_0163","CNzh":"<unk[3:0:7]><unk[4:0:30 84 97 108 107 80 111 115 105 116 105 118 101 95 48 49]>真是一直受你帮助呢。","TWzh":"<unk[3:0:7]><unk[4:0:30 84 97 108 107 80 111 115 105 116 105 118 101 95 48 49]>我總是得到你的幫助呢。","JPja":"<unk[3:0:7]><unk[4:0:30 84 97 108 107 80 111 115 105 116 105 118 101 95 48 49]>お<Ruby={2:4}まえ>前には <Ruby={2:4}たす>助けられてばかりだな","USen":"<unk[3:0:7]><unk[4:0:30 84 97 108 107 80 111 115 105 116 105 118 101 95 48 49]>You've already helped me so much."},{"id":14111,"index":172,"key":"Talk_0178","CNzh":"如果你要去<Color=red>格鲁德小镇<Color=white>的话，\n记得帮我们看一眼微达。","TWzh":"如果你有經過<Color=red>格魯德小鎮<Color=white>，\n就替我們照看一下微達吧。","JPja":"もし<Color=red>ゲルドの<Ruby={2:4}まち>街<Color=white>を<Ruby={2:4}たず>訪ねることがあれば\nウィッダのこと <Ruby={2:2}き>気にかけてやってくれ","USen":"But if you ever visit <Color=red>Gerudo Town<Color=white>, please\ncheck in on Mattison."},{"id":14112,"index":173,"key":"Talk_0196","CNzh":"<unk[3:0:7]><unk[4:0:22 71 114 101 101 116 105 110 103 95 48 48]>你在说什么呢？\n格鲁德小镇不是禁止伯伊入内吗？","TWzh":"<unk[3:0:7]><unk[4:0:22 71 114 101 101 116 105 110 103 95 48 48]>你在說什麼呢，\n你忘記格魯德小鎮禁止伯伊進入了嗎？","JPja":"<unk[3:0:7]><unk[4:0:22 71 114 101 101 116 105 110 103 95 48 48]><Ruby={4:6}なにい>何言ってるのよ<unk[5:1]>\nゲルドの<Ruby={2:4}まち>街はヴォーイ<Ruby={4:8}きんせい>禁制よ <unk[5:0]><Ruby={2:4}わす>忘れたの？","USen":"<unk[3:0:7]><unk[4:0:22 71 114 101 101 116 105 110 103 95 48 48]>What are you talking about? Have you\nforgotten that voe aren't allowed in\nGerudo Town?"},{"id":14113,"index":174,"key":"Talk_0197","CNzh":"<unk[3:0:7]><unk[4:0:18 78 111 116 105 99 101 95 48 49]>啊，对哦，\n我把这个给忘了。","TWzh":"<unk[3:0:7]><unk[4:0:18 78 111 116 105 99 101 95 48 49]>啊，說得也是，\n一不小心就忘記了。","JPja":"<unk[3:0:7]><unk[4:0:18 78 111 116 105 99 101 95 48 49]>ああ そうだったな<unk[5:0]>\nうっかりしていたよ","USen":"<unk[3:0:7]><unk[4:0:18 78 111 116 105 99 101 95 48 49]>Ah, right. I guess it slipped my mind."},{"id":14114,"index":175,"key":"Talk_0202","CNzh":"<unk[3:0:7]><unk[4:0:18 76 97 117 103 104 83 95 48 49]>走吧，该回去工作了。\n肯定有客人在等着我们开业吧？","TWzh":"<unk[3:0:7]><unk[4:0:18 76 97 117 103 104 83 95 48 49]>好了，我們該回去工作了。\n老公，一定有客人在等你對吧？","JPja":"<unk[3:0:7]><unk[4:0:18 76 97 117 103 104 83 95 48 49]>さ <Ruby={4:6}しごと>仕事に<Ruby={2:4}もど>戻るわよ<unk[5:1]>\nアナタ <Ruby={2:2}ま>待たせているお<Ruby={4:10}きゃくさま>客様がいるんでしょ？","USen":"<unk[3:0:7]><unk[4:0:18 76 97 117 103 104 83 95 48 49]>Now, I've got to get back to work.\nDon't you have a customer waiting\nfor you, dear?"},{"id":14115,"index":176,"key":"Talk_0203","CNzh":"<unk[3:0:7]><unk[4:0:18 76 97 117 103 104 83 95 48 49]>走吧，该回去工作了。\n我们得继续受理<Color=red>私人住宅<Color=white>的事务呢。","TWzh":"<unk[3:0:7]><unk[4:0:18 76 97 117 103 104 83 95 48 49]>好了，我們該回去工作了。\n還得重新受理<Color=red>個人小屋<Color=white>業務才行。","JPja":"<unk[3:0:7]><unk[4:0:18 76 97 117 103 104 83 95 48 49]>さ <Ruby={4:6}しごと>仕事に<Ruby={2:4}もど>戻るわよ<unk[5:1]>\n<Color=red>マイホーム<Color=white>の<Ruby={4:8}うけつけ>受付も<Ruby={4:8}さいかい>再開しなきゃ","USen":"<unk[3:0:7]><unk[4:0:18 76 97 117 103 104 83 95 48 49]>I've got to be getting back to work.\nWe need to start accepting requests\nfor <Color=red>dream homes <Color=white>again."}]}